<?xml version="1.0" encoding="utf-8"?>
<maps index="21">
  <!--<map>
    <name>map14</name>
    <width>9</width>
    <height>70</height>
    <content>
1/-1/-1 1/-1/-1 1/-1/-1 1/-1/-1 1/-1/-1 1/-1/-1 1/-1/-1 1/-1/-1 1/-1/-1 
1/-1/-1 -1/-1/-1 -1/-1/-1 -1/-1/-1 -1/-1/-1 -1/-1/-1 -1/-1/-1 -1/-1/-1 1/-1/-1 
1/-1/-1 -1/-1/-1 -1/-1/-1 -1/-1/-1 -1/-1/-1 -1/-1/-1 -1/-1/-1 -1/-1/-1 1/-1/-1 
1/-1/-1 -1/-1/-1 -1/-1/-1 -1/-1/-1 -1/-1/-1 -1/-1/-1 -1/-1/-1 -1/-1/-1 1/-1/-1 
1/-1/-1 -1/-1/-1 -1/-1/-1 -1/-1/-1 -1/-1/-1 -1/-1/-1 -1/-1/-1 -1/-1/-1 1/-1/-1 
1/-1/-1 -1/-1/-1 -1/-1/-1 -1/-1/-1 -1/-1/-1 -1/-1/-1 -1/-1/-1 -1/-1/-1 1/-1/-1 
1/-1/-1 -1/-1/-1 -1/-1/-1 -1/-1/-1 -1/-1/-1 -1/-1/-1 -1/-1/-1 -1/-1/-1 1/-1/-1 
1/-1/-1 -1/-1/-1 -1/-1/-1 -1/-1/-1 -1/-1/-1 -1/-1/-1 -1/-1/-1 -1/-1/-1 1/-1/-1 
1/-1/-1 -1/-1/-1 -1/-1/-1 -1/-1/-1 -1/-1/-1 -1/-1/-1 -1/-1/-1 -1/-1/-1 1/-1/-1 
1/-1/-1 -1/-1/-1 -1/-1/-1 -1/-1/-1 -1/-1/-1 -1/-1/-1 -1/-1/-1 -1/-1/-1 1/-1/-1 
1/-1/-1 -1/-1/-1 -1/-1/-1 -1/-1/-1 -1/-1/-1 -1/-1/-1 -1/-1/-1 -1/-1/-1 1/-1/-1 
1/-1/-1 -1/-1/-1 -1/-1/-1 -1/-1/-1 -1/-1/-1 -1/-1/-1 -1/-1/-1 -1/-1/-1 1/-1/-1 
1/-1/-1 -1/-1/-1 -1/-1/-1 -1/-1/-1 -1/-1/-1 -1/-1/-1 -1/-1/-1 -1/-1/-1 1/-1/-1 
1/-1/-1 -1/-1/-1 -1/-1/-1 -1/-1/-1 -1/-1/-1 -1/-1/-1 -1/-1/-1 -1/-1/-1 1/-1/-1 
1/-1/-1 -1/-1/-1 -1/-1/-1 -1/-1/-1 -1/-1/-1 -1/-1/-1 -1/-1/-1 -1/-1/-1 1/-1/-1 
1/-1/-1 -1/-1/-1 -1/-1/-1 -1/-1/-1 -1/-1/-1 -1/-1/-1 -1/-1/-1 -1/-1/-1 1/-1/-1 
1/-1/-1 -1/-1/-1 -1/-1/-1 -1/-1/-1 -1/-1/-1 -1/-1/-1 -1/-1/-1 -1/-1/-1 1/-1/-1 
1/-1/-1 -1/-1/-1 -1/-1/-1 -1/-1/-1 -1/-1/-1 -1/-1/-1 -1/-1/-1 -1/-1/-1 1/-1/-1 
1/-1/-1 -1/-1/-1 -1/-1/-1 -1/-1/-1 -1/-1/-1 -1/-1/-1 -1/-1/-1 -1/-1/-1 1/-1/-1 
1/-1/-1 -1/-1/-1 -1/-1/-1 -1/-1/-1 -1/-1/-1 -1/-1/-1 -1/-1/-1 -1/-1/-1 1/-1/-1 
1/-1/-1 -1/-1/-1 -1/-1/-1 -1/-1/-1 -1/-1/-1 -1/-1/-1 -1/-1/-1 -1/-1/-1 1/-1/-1 
1/-1/-1 -1/-1/-1 -1/-1/-1 -1/-1/-1 -1/-1/-1 -1/-1/-1 -1/-1/-1 -1/-1/-1 1/-1/-1 
1/-1/-1 -1/-1/-1 -1/-1/-1 -1/-1/-1 -1/-1/-1 -1/-1/-1 -1/-1/-1 -1/-1/-1 1/-1/-1 
1/-1/-1 -1/-1/-1 -1/-1/-1 -1/-1/-1 -1/-1/-1 -1/-1/-1 -1/-1/-1 -1/-1/-1 1/-1/-1 
1/-1/-1 -1/-1/-1 -1/-1/-1 -1/-1/-1 -1/-1/-1 -1/-1/-1 -1/-1/-1 -1/-1/-1 1/-1/-1 
1/-1/-1 -1/-1/-1 -1/-1/-1 -1/-1/-1 -1/-1/-1 -1/-1/-1 -1/-1/-1 -1/-1/-1 1/-1/-1 
1/-1/-1 -1/-1/-1 -1/-1/-1 -1/-1/-1 -1/-1/-1 -1/-1/-1 -1/-1/-1 -1/-1/-1 1/-1/-1 
1/-1/-1 -1/-1/-1 -1/-1/-1 -1/-1/-1 -1/-1/-1 -1/-1/-1 -1/-1/-1 -1/-1/-1 1/-1/-1 
1/-1/-1 -1/-1/-1 -1/-1/-1 -1/-1/-1 -1/-1/-1 -1/-1/-1 -1/-1/-1 -1/-1/-1 1/-1/-1 
1/-1/-1 -1/-1/-1 -1/-1/-1 -1/-1/-1 -1/-1/-1 -1/-1/-1 -1/-1/-1 -1/-1/-1 1/-1/-1 
1/-1/-1 -1/-1/-1 -1/-1/-1 -1/-1/-1 -1/-1/-1 -1/-1/-1 -1/-1/-1 -1/-1/-1 1/-1/-1 
1/-1/-1 -1/-1/-1 -1/-1/-1 -1/-1/-1 -1/-1/-1 -1/-1/-1 -1/-1/-1 -1/-1/-1 1/-1/-1 
1/-1/-1 -1/-1/-1 -1/-1/-1 -1/-1/-1 -1/-1/-1 -1/-1/-1 -1/-1/-1 -1/-1/-1 1/-1/-1 
1/-1/-1 -1/-1/-1 -1/-1/-1 -1/-1/-1 -1/-1/-1 -1/-1/-1 -1/-1/-1 -1/-1/-1 1/-1/-1 
1/-1/-1 -1/-1/-1 -1/-1/-1 -1/-1/-1 -1/-1/-1 -1/-1/-1 -1/-1/-1 -1/-1/-1 1/-1/-1 
1/-1/-1 -1/-1/-1 -1/-1/-1 -1/-1/-1 -1/-1/-1 -1/-1/-1 -1/-1/-1 -1/-1/-1 1/-1/-1 
1/-1/-1 -1/-1/-1 -1/-1/-1 -1/-1/-1 -1/-1/-1 -1/-1/-1 -1/-1/-1 -1/-1/-1 1/-1/-1 
1/-1/-1 -1/-1/-1 -1/-1/-1 -1/-1/-1 -1/-1/-1 -1/-1/-1 -1/-1/-1 -1/-1/-1 1/-1/-1 
1/-1/-1 -1/-1/-1 -1/-1/-1 -1/-1/-1 -1/-1/-1 -1/-1/-1 -1/-1/-1 -1/-1/-1 1/-1/-1 
1/-1/-1 -1/-1/-1 -1/-1/-1 -1/-1/-1 -1/-1/-1 -1/-1/-1 -1/-1/-1 -1/-1/-1 1/-1/-1 
1/-1/-1 -1/-1/-1 -1/-1/-1 -1/-1/-1 -1/-1/-1 -1/-1/-1 -1/-1/-1 -1/-1/-1 1/-1/-1 
1/-1/-1 -1/-1/-1 -1/-1/-1 -1/-1/-1 -1/-1/-1 -1/-1/-1 -1/-1/-1 -1/-1/-1 1/-1/-1 
1/-1/-1 -1/-1/-1 -1/-1/-1 -1/-1/-1 -1/-1/-1 -1/-1/-1 -1/-1/-1 -1/-1/-1 1/-1/-1 
1/-1/-1 -1/-1/-1 -1/-1/-1 -1/-1/-1 -1/-1/-1 -1/-1/-1 -1/-1/-1 -1/-1/-1 1/-1/-1 
1/-1/-1 -1/-1/-1 -1/-1/-1 -1/-1/-1 -1/-1/-1 -1/-1/-1 -1/-1/-1 -1/-1/-1 1/-1/-1 
1/-1/-1 -1/-1/-1 -1/-1/-1 -1/-1/-1 -1/-1/-1 -1/-1/-1 -1/-1/-1 -1/-1/-1 1/-1/-1 
1/-1/-1 -1/-1/-1 -1/-1/-1 -1/-1/-1 -1/-1/-1 -1/-1/-1 -1/-1/-1 -1/-1/-1 1/-1/-1 
1/-1/-1 -1/-1/-1 -1/-1/-1 -1/-1/-1 -1/-1/-1 -1/-1/-1 -1/-1/-1 -1/-1/-1 1/-1/-1 
1/-1/-1 -1/-1/-1 -1/-1/-1 -1/-1/-1 -1/-1/-1 -1/-1/-1 -1/-1/-1 -1/-1/-1 1/-1/-1 
1/-1/-1 -1/-1/-1 -1/-1/-1 -1/-1/-1 -1/-1/-1 -1/-1/-1 -1/-1/-1 -1/-1/-1 1/-1/-1 
1/-1/-1 -1/-1/-1 -1/-1/-1 -1/-1/-1 -1/-1/-1 -1/-1/-1 -1/-1/-1 -1/-1/-1 1/-1/-1 
1/-1/-1 -1/-1/-1 -1/-1/-1 -1/-1/-1 -1/-1/-1 -1/-1/-1 -1/-1/-1 -1/-1/-1 1/-1/-1 
1/-1/-1 -1/-1/-1 -1/-1/-1 -1/-1/-1 -1/-1/-1 -1/-1/-1 -1/-1/-1 -1/-1/-1 1/-1/-1 
1/-1/-1 -1/-1/-1 -1/-1/-1 -1/-1/-1 -1/-1/-1 -1/-1/-1 -1/-1/-1 -1/-1/-1 1/-1/-1 
1/-1/-1 -1/-1/-1 -1/-1/-1 -1/-1/-1 -1/-1/-1 -1/-1/-1 -1/-1/-1 -1/-1/-1 1/-1/-1 
1/-1/-1 -1/-1/-1 -1/-1/-1 -1/-1/-1 -1/-1/-1 -1/-1/-1 -1/-1/-1 -1/-1/-1 1/-1/-1 
1/-1/-1 -1/-1/-1 -1/-1/-1 -1/-1/-1 -1/-1/-1 -1/-1/-1 -1/-1/-1 -1/-1/-1 1/-1/-1 
1/-1/-1 -1/-1/-1 -1/-1/-1 -1/-1/-1 -1/-1/-1 -1/-1/-1 -1/-1/-1 -1/-1/-1 1/-1/-1 
1/-1/-1 -1/-1/-1 -1/-1/-1 -1/-1/-1 -1/-1/-1 -1/-1/-1 -1/-1/-1 -1/-1/-1 1/-1/-1 
1/-1/-1 -1/-1/-1 -1/-1/-1 -1/-1/-1 -1/-1/-1 -1/-1/-1 -1/-1/-1 -1/-1/-1 1/-1/-1 
1/-1/-1 -1/-1/-1 -1/-1/-1 -1/-1/-1 -1/-1/-1 -1/-1/-1 -1/-1/-1 -1/-1/-1 1/-1/-1 
1/-1/-1 -1/-1/-1 -1/-1/-1 -1/-1/-1 -1/-1/-1 -1/-1/-1 -1/-1/-1 -1/-1/-1 1/-1/-1 
1/-1/-1 -1/-1/-1 -1/-1/-1 -1/-1/-1 -1/-1/-1 -1/-1/-1 -1/-1/-1 -1/-1/-1 1/-1/-1 
1/-1/-1 -1/-1/-1 -1/-1/-1 -1/-1/-1 -1/-1/-1 -1/-1/-1 -1/-1/-1 -1/-1/-1 1/-1/-1 
1/-1/-1 -1/-1/-1 -1/-1/-1 -1/-1/-1 -1/-1/-1 -1/-1/-1 -1/-1/-1 -1/-1/-1 1/-1/-1 
1/-1/-1 -1/-1/-1 -1/-1/-1 -1/-1/-1 -1/-1/-1 -1/-1/-1 -1/-1/-1 -1/-1/-1 1/-1/-1 
1/-1/-1 -1/-1/-1 -1/-1/-1 -1/-1/-1 -1/-1/-1 -1/-1/-1 -1/-1/-1 -1/-1/-1 1/-1/-1 
1/-1/-1 -1/-1/-1 -1/-1/-1 -1/-1/-1 -1/-1/-1 -1/-1/-1 -1/-1/-1 -1/-1/-1 1/-1/-1 
1/-1/-1 -1/-1/-1 -1/-1/-1 -1/-1/-1 -1/-1/-1 -1/-1/-1 -1/-1/-1 -1/-1/-1 1/-1/-1 
1/-1/-1 1/-1/-1 1/-1/-1 1/-1/-1 1/-1/-1 1/-1/-1 1/-1/-1 1/-1/-1 1/-1/-1 
</content>
    <position>4 1</position>
    <gravity>1</gravity>
    <next-map>map14</next-map>
  </map>
  <map>
    <name>map15</name>
    <width>15</width>
    <height>50</height>
    <content>
1/-1/-1 1/-1/-1 1/-1/-1 1/-1/-1 1/-1/-1 1/-1/-1 1/-1/-1 1/-1/-1 1/-1/-1 1/-1/-1 1/-1/-1 1/-1/-1 1/-1/-1 1/-1/-1 1/-1/-1 
1/-1/-1 -1/-1/-1 -1/-1/-1 2/-1/-1 -1/-1/-1 -1/-1/-1 -1/-1/-1 -1/-1/-1 -1/-1/-1 -1/-1/-1 -1/-1/-1 -1/-1/-1 -1/-1/-1 -1/-1/-1 1/-1/-1 
1/-1/-1 -1/-1/-1 -1/-1/-1 -1/-1/-1 -1/-1/-1 -1/-1/-1 -1/-1/-1 -1/-1/-1 -1/-1/-1 -1/-1/-1 -1/-1/-1 -1/-1/-1 2/-1/-1 -1/-1/-1 1/-1/-1 
1/-1/-1 -1/-1/-1 -1/-1/-1 -1/-1/-1 -1/-1/-1 -1/-1/-1 -1/-1/-1 -1/-1/-1 -1/-1/-1 -1/-1/-1 -1/-1/-1 -1/-1/-1 -1/-1/-1 -1/-1/-1 1/-1/-1 
1/-1/-1 -1/-1/-1 -1/-1/-1 -1/-1/-1 -1/-1/-1 -1/-1/-1 -1/-1/-1 -1/-1/-1 -1/-1/-1 -1/-1/-1 -1/-1/-1 -1/-1/-1 -1/-1/-1 -1/-1/-1 1/-1/-1 
1/-1/-1 1/-1/-1 1/-1/-1 1/-1/-1 1/-1/-1 1/-1/-1 -1/-1/-1 -1/-1/-1 -1/-1/-1 1/-1/-1 1/-1/-1 1/-1/-1 1/-1/-1 1/-1/-1 1/-1/-1 
1/-1/-1 -1/-1/-1 -1/-1/-1 -1/-1/-1 -1/-1/-1 -1/-1/-1 -1/-1/-1 -1/-1/-1 -1/-1/-1 -1/-1/-1 -1/-1/-1 -1/-1/-1 -1/-1/-1 -1/-1/-1 1/-1/-1 
1/-1/-1 -1/-1/-1 -1/-1/-1 -1/-1/-1 -1/-1/-1 -1/-1/-1 -1/-1/-1 -1/-1/-1 -1/-1/-1 -1/-1/-1 -1/-1/-1 -1/-1/-1 -1/-1/-1 -1/-1/-1 1/-1/-1 
1/-1/-1 -1/-1/-1 -1/-1/-1 -1/-1/-1 -1/-1/-1 -1/-1/-1 -1/-1/-1 -1/-1/-1 -1/-1/-1 -1/-1/-1 -1/-1/-1 2/-1/-1 -1/-1/-1 -1/-1/-1 1/-1/-1 
1/-1/-1 -1/-1/-1 -1/-1/-1 -1/-1/-1 -1/-1/-1 -1/-1/-1 -1/-1/-1 -1/-1/-1 -1/-1/-1 -1/-1/-1 -1/-1/-1 -1/-1/-1 -1/-1/-1 -1/-1/-1 1/-1/-1 
1/-1/-1 -1/-1/-1 -1/-1/-1 -1/-1/-1 -1/-1/-1 -1/-1/-1 -1/-1/-1 -1/-1/-1 -1/-1/-1 -1/-1/-1 -1/-1/-1 -1/-1/-1 -1/-1/-1 -1/-1/-1 1/-1/-1 
1/-1/-1 -1/-1/-1 -1/-1/-1 -1/-1/-1 -1/-1/-1 -1/-1/-1 -1/-1/-1 -1/-1/-1 -1/-1/-1 -1/-1/-1 -1/-1/-1 -1/-1/-1 -1/-1/-1 -1/-1/-1 1/-1/-1 
1/-1/-1 -1/-1/-1 -1/-1/-1 -1/-1/-1 -1/-1/-1 -1/-1/-1 -1/-1/-1 -1/-1/-1 -1/-1/-1 -1/-1/-1 -1/-1/-1 -1/-1/-1 -1/-1/-1 -1/-1/-1 1/-1/-1 
1/-1/-1 -1/-1/-1 -1/-1/-1 -1/-1/-1 -1/-1/-1 2/-1/-1 -1/-1/-1 -1/-1/-1 -1/-1/-1 2/-1/-1 -1/-1/-1 -1/-1/-1 -1/-1/-1 -1/-1/-1 1/-1/-1 
1/-1/-1 -1/-1/-1 -1/-1/-1 -1/-1/-1 -1/-1/-1 -1/-1/-1 -1/-1/-1 -1/-1/-1 -1/-1/-1 -1/-1/-1 -1/-1/-1 -1/-1/-1 -1/-1/-1 -1/-1/-1 1/-1/-1 
1/-1/-1 -1/-1/-1 -1/-1/-1 -1/-1/-1 -1/-1/-1 -1/-1/-1 -1/-1/-1 -1/-1/-1 -1/-1/-1 -1/-1/-1 -1/-1/-1 -1/-1/-1 -1/-1/-1 -1/-1/-1 1/-1/-1 
1/-1/-1 -1/-1/-1 -1/-1/-1 -1/-1/-1 -1/-1/-1 -1/-1/-1 -1/-1/-1 -1/-1/-1 -1/-1/-1 -1/-1/-1 -1/-1/-1 -1/-1/-1 -1/-1/-1 -1/-1/-1 1/-1/-1 
1/-1/-1 -1/-1/-1 2/-1/-1 -1/-1/-1 -1/-1/-1 -1/-1/-1 -1/-1/-1 -1/-1/-1 -1/-1/-1 -1/-1/-1 -1/-1/-1 -1/-1/-1 -1/-1/-1 -1/-1/-1 1/-1/-1 
1/-1/-1 -1/-1/-1 -1/-1/-1 -1/-1/-1 -1/-1/-1 -1/-1/-1 -1/-1/-1 -1/-1/-1 -1/-1/-1 -1/-1/-1 -1/-1/-1 -1/-1/-1 -1/-1/-1 -1/-1/-1 1/-1/-1 
1/-1/-1 -1/-1/-1 -1/-1/-1 -1/-1/-1 -1/-1/-1 -1/-1/-1 -1/-1/-1 -1/-1/-1 -1/-1/-1 -1/-1/-1 -1/-1/-1 -1/-1/-1 -1/-1/-1 -1/-1/-1 1/-1/-1 
1/-1/-1 -1/-1/-1 -1/-1/-1 -1/-1/-1 -1/-1/-1 -1/-1/-1 -1/-1/-1 -1/-1/-1 -1/-1/-1 -1/-1/-1 -1/-1/-1 -1/-1/-1 -1/-1/-1 -1/-1/-1 1/-1/-1 
1/-1/-1 -1/-1/-1 -1/-1/-1 -1/-1/-1 13/-1/-1 -1/-1/-1 -1/-1/-1 13/-1/-1 -1/-1/-1 -1/-1/-1 -1/-1/-1 -1/-1/-1 -1/-1/-1 -1/-1/-1 1/-1/-1 
1/-1/-1 -1/-1/-1 -1/-1/-1 -1/-1/-1 -1/-1/-1 -1/-1/-1 -1/-1/-1 -1/-1/-1 -1/-1/-1 -1/-1/-1 -1/-1/-1 -1/-1/-1 -1/-1/-1 -1/-1/-1 1/-1/-1 
1/-1/-1 -1/-1/-1 -1/-1/-1 -1/-1/-1 -1/-1/-1 -1/-1/-1 -1/-1/-1 -1/-1/-1 -1/-1/-1 -1/-1/-1 -1/-1/-1 -1/-1/-1 -1/-1/-1 -1/-1/-1 1/-1/-1 
1/-1/-1 -1/-1/-1 -1/-1/-1 -1/-1/-1 -1/-1/-1 -1/-1/-1 -1/-1/-1 -1/-1/-1 -1/-1/-1 -1/-1/-1 -1/-1/-1 -1/-1/-1 -1/-1/-1 -1/-1/-1 1/-1/-1 
1/-1/-1 -1/-1/-1 -1/-1/-1 -1/-1/-1 -1/-1/-1 -1/-1/-1 -1/-1/-1 -1/-1/-1 -1/-1/-1 -1/-1/-1 -1/-1/-1 -1/-1/-1 -1/-1/-1 -1/-1/-1 1/-1/-1 
1/-1/-1 -1/-1/-1 -1/-1/-1 -1/-1/-1 -1/-1/-1 -1/-1/-1 -1/-1/-1 -1/-1/-1 -1/-1/-1 -1/-1/-1 -1/-1/-1 -1/-1/-1 -1/-1/-1 -1/-1/-1 1/-1/-1 
1/-1/-1 -1/-1/-1 -1/-1/-1 -1/-1/-1 -1/-1/-1 -1/-1/-1 -1/-1/-1 -1/-1/-1 -1/-1/-1 -1/-1/-1 -1/-1/-1 -1/-1/-1 -1/-1/-1 -1/-1/-1 1/-1/-1 
1/-1/-1 -1/-1/-1 -1/-1/-1 -1/-1/-1 -1/-1/-1 -1/-1/-1 -1/-1/-1 -1/-1/-1 -1/-1/-1 -1/-1/-1 -1/-1/-1 -1/-1/-1 -1/-1/-1 -1/-1/-1 1/-1/-1 
1/-1/-1 -1/-1/-1 -1/-1/-1 -1/-1/-1 -1/-1/-1 -1/-1/-1 -1/-1/-1 -1/-1/-1 -1/-1/-1 -1/-1/-1 -1/-1/-1 -1/-1/-1 -1/-1/-1 -1/-1/-1 1/-1/-1 
1/-1/-1 -1/-1/-1 -1/-1/-1 -1/-1/-1 -1/-1/-1 -1/-1/-1 -1/-1/-1 -1/-1/-1 -1/-1/-1 -1/-1/-1 -1/-1/-1 -1/-1/-1 -1/-1/-1 -1/-1/-1 1/-1/-1 
1/-1/-1 -1/-1/-1 -1/-1/-1 -1/-1/-1 -1/-1/-1 -1/-1/-1 -1/-1/-1 -1/-1/-1 -1/-1/-1 -1/-1/-1 -1/-1/-1 -1/-1/-1 -1/-1/-1 -1/-1/-1 1/-1/-1 
1/-1/-1 -1/-1/-1 -1/-1/-1 -1/-1/-1 -1/-1/-1 -1/-1/-1 -1/-1/-1 -1/-1/-1 -1/-1/-1 -1/-1/-1 -1/-1/-1 -1/-1/-1 -1/-1/-1 -1/-1/-1 1/-1/-1 
1/-1/-1 -1/-1/-1 -1/-1/-1 -1/-1/-1 -1/-1/-1 -1/-1/-1 -1/-1/-1 -1/-1/-1 -1/-1/-1 -1/-1/-1 -1/-1/-1 -1/-1/-1 -1/-1/-1 -1/-1/-1 1/-1/-1 
1/-1/-1 -1/-1/-1 -1/-1/-1 -1/-1/-1 -1/-1/-1 -1/-1/-1 -1/-1/-1 -1/-1/-1 -1/-1/-1 -1/-1/-1 -1/-1/-1 -1/-1/-1 -1/-1/-1 -1/-1/-1 1/-1/-1 
1/-1/-1 -1/-1/-1 -1/-1/-1 -1/-1/-1 -1/-1/-1 -1/-1/-1 -1/-1/-1 -1/-1/-1 -1/-1/-1 -1/-1/-1 -1/-1/-1 -1/-1/-1 -1/-1/-1 -1/-1/-1 1/-1/-1 
1/-1/-1 -1/-1/-1 -1/-1/-1 -1/-1/-1 -1/-1/-1 -1/-1/-1 -1/-1/-1 -1/-1/-1 -1/-1/-1 -1/-1/-1 -1/-1/-1 -1/-1/-1 -1/-1/-1 -1/-1/-1 1/-1/-1 
1/-1/-1 -1/-1/-1 -1/-1/-1 -1/-1/-1 -1/-1/-1 -1/-1/-1 -1/-1/-1 -1/-1/-1 -1/-1/-1 -1/-1/-1 -1/-1/-1 -1/-1/-1 -1/-1/-1 -1/-1/-1 1/-1/-1 
1/-1/-1 -1/-1/-1 -1/-1/-1 -1/-1/-1 -1/-1/-1 -1/-1/-1 -1/-1/-1 -1/-1/-1 -1/-1/-1 -1/-1/-1 -1/-1/-1 -1/-1/-1 -1/-1/-1 -1/-1/-1 1/-1/-1 
1/-1/-1 -1/-1/-1 -1/-1/-1 -1/-1/-1 -1/-1/-1 -1/-1/-1 -1/-1/-1 -1/-1/-1 -1/-1/-1 -1/-1/-1 -1/-1/-1 -1/-1/-1 -1/-1/-1 -1/-1/-1 1/-1/-1 
1/-1/-1 -1/-1/-1 -1/-1/-1 -1/-1/-1 -1/-1/-1 -1/-1/-1 -1/-1/-1 -1/-1/-1 -1/-1/-1 -1/-1/-1 -1/-1/-1 -1/-1/-1 -1/-1/-1 -1/-1/-1 1/-1/-1 
1/-1/-1 16/-1/-1 -1/-1/-1 1/-1/-1 -1/-1/-1 -1/-1/-1 -1/-1/-1 -1/-1/-1 -1/-1/-1 -1/-1/-1 -1/-1/-1 -1/-1/-1 -1/-1/-1 -1/-1/-1 1/-1/-1 
1/-1/-1 -1/-1/-1 -1/-1/-1 1/-1/-1 -1/-1/-1 -1/-1/-1 -1/-1/-1 -1/-1/-1 -1/-1/-1 -1/-1/-1 -1/-1/-1 -1/-1/-1 -1/-1/-1 -1/-1/-1 1/-1/-1 
1/-1/-1 -1/-1/-1 -1/-1/-1 1/-1/-1 -1/-1/-1 -1/-1/-1 -1/-1/-1 -1/-1/-1 -1/-1/-1 -1/-1/-1 -1/-1/-1 -1/-1/-1 -1/-1/-1 -1/-1/-1 1/-1/-1 
1/-1/-1 -1/-1/-1 -1/-1/-1 1/-1/-1 -1/-1/-1 -1/-1/-1 -1/-1/-1 -1/-1/-1 -1/-1/-1 -1/-1/-1 -1/-1/-1 -1/-1/-1 -1/-1/-1 -1/-1/-1 1/-1/-1 
1/-1/-1 -1/-1/-1 -1/-1/-1 1/-1/-1 -1/-1/-1 -1/-1/-1 -1/-1/-1 -1/-1/-1 -1/-1/-1 -1/-1/-1 -1/-1/-1 -1/-1/-1 -1/-1/-1 -1/-1/-1 1/-1/-1 
1/-1/-1 -1/-1/-1 -1/-1/-1 -1/-1/-1 -1/-1/-1 -1/-1/-1 -1/-1/-1 -1/-1/-1 -1/-1/-1 -1/-1/-1 -1/-1/-1 -1/-1/-1 -1/-1/-1 -1/-1/-1 1/-1/-1 
1/-1/-1 -1/-1/-1 -1/-1/-1 -1/-1/-1 -1/-1/-1 -1/-1/-1 -1/-1/-1 -1/-1/-1 -1/-1/-1 -1/-1/-1 -1/-1/-1 -1/-1/-1 -1/-1/-1 -1/-1/-1 1/-1/-1 
1/-1/-1 -1/-1/-1 -1/-1/-1 -1/-1/-1 -1/-1/-1 -1/-1/-1 -1/-1/-1 -1/-1/-1 -1/-1/-1 -1/-1/-1 -1/-1/-1 -1/-1/-1 -1/-1/-1 -1/-1/-1 1/-1/-1 
1/-1/-1 1/-1/-1 1/-1/-1 1/-1/-1 1/-1/-1 1/-1/-1 1/-1/-1 1/-1/-1 1/-1/-1 1/-1/-1 1/-1/-1 1/-1/-1 1/-1/-1 1/-1/-1 1/-1/-1 
</content>
    <position>3 4</position>
    <gravity>1</gravity>
    <next-map>map15</next-map>
  </map>
  <map>
    <name>Stage 2</name>
    <width>40</width>
    <height>40</height>
    <content>
1/-1/-1 1/-1/-1 1/-1/-1 1/-1/-1 1/-1/-1 1/-1/-1 1/-1/-1 1/-1/-1 1/-1/-1 1/-1/-1 1/-1/-1 1/-1/-1 1/-1/-1 1/-1/-1 1/-1/-1 1/-1/-1 1/-1/-1 1/-1/-1 1/-1/-1 1/-1/-1 -1/-1/-1 -1/-1/-1 -1/-1/-1 -1/-1/-1 -1/-1/-1 -1/-1/-1 -1/-1/-1 -1/-1/-1 -1/-1/-1 -1/-1/-1 -1/-1/-1 -1/-1/-1 -1/-1/-1 -1/-1/-1 -1/-1/-1 -1/-1/-1 -1/-1/-1 -1/-1/-1 -1/-1/-1 -1/-1/-1 
1/-1/-1 -1/-1/-1 -1/-1/-1 -1/-1/-1 -1/-1/-1 -1/-1/-1 1/-1/-1 1/-1/-1 2/-1/-1 -1/-1/-1 -1/-1/-1 -1/-1/-1 -1/-1/-1 -1/-1/-1 -1/-1/-1 1/-1/-1 1/-1/-1 -1/7/-1 -1/7/-1 1/-1/-1 1/-1/-1 1/-1/-1 1/-1/-1 1/-1/-1 1/-1/-1 1/-1/-1 1/-1/-1 1/-1/-1 -1/-1/-1 -1/-1/-1 -1/-1/-1 -1/-1/-1 -1/-1/-1 -1/-1/-1 -1/-1/-1 -1/-1/-1 -1/-1/-1 -1/-1/-1 -1/-1/-1 -1/-1/-1 
1/-1/-1 -1/-1/-1 2/-1/-1 -1/-1/-1 2/-1/-1 -1/-1/-1 -1/-1/-1 1/-1/-1 1/-1/-1 -1/-1/-1 -1/-1/-1 -1/-1/-1 -1/-1/-1 -1/-1/-1 -1/-1/-1 1/-1/-1 1/-1/-1 -1/7/-1 -1/7/-1 1/-1/-1 -1/-1/-1 -1/-1/-1 -1/-1/-1 -1/-1/-1 -1/-1/-1 -1/-1/-1 -1/-1/-1 1/-1/-1 -1/-1/-1 -1/-1/-1 -1/-1/-1 -1/-1/-1 -1/-1/-1 -1/-1/-1 -1/-1/-1 -1/-1/-1 -1/-1/-1 -1/-1/-1 -1/-1/-1 -1/-1/-1 
1/-1/-1 -1/-1/-1 -1/-1/-1 -1/-1/-1 -1/-1/-1 -1/-1/-1 -1/-1/-1 -1/-1/-1 1/-1/-1 1/-1/-1 -1/1/-1 -1/1/-1 -1/1/-1 -1/1/-1 -1/1/-1 1/-1/-1 1/-1/-1 -1/-1/-1 -1/-1/-1 1/-1/-1 -1/-1/-1 1/-1/-1 1/-1/-1 1/-1/-1 1/-1/-1 1/-1/-1 -1/-1/-1 1/-1/-1 1/-1/-1 -1/-1/-1 -1/-1/-1 -1/-1/-1 -1/-1/-1 -1/-1/-1 -1/-1/-1 -1/-1/-1 -1/-1/-1 -1/-1/-1 -1/-1/-1 -1/-1/-1 
1/-1/-1 -1/-1/-1 -1/-1/-1 -1/-1/-1 -1/-1/-1 -1/-1/-1 -1/-1/-1 -1/-1/-1 -1/-1/-1 1/-1/-1 1/-1/-1 -1/1/-1 -1/1/-1 -1/1/-1 -1/1/-1 1/-1/-1 1/-1/-1 -1/-1/-1 -1/-1/-1 -1/1/-1 -1/-1/-1 1/-1/-1 1/-1/-1 1/-1/-1 1/-1/-1 1/-1/-1 -1/-1/-1 -1/-1/-1 1/-1/-1 1/-1/-1 -1/-1/-1 -1/-1/-1 -1/-1/-1 -1/-1/-1 -1/-1/-1 -1/-1/-1 -1/-1/-1 -1/-1/-1 -1/-1/-1 -1/-1/-1 
1/-1/-1 1/-1/-1 1/-1/-1 1/-1/-1 1/-1/-1 1/-1/-1 1/-1/-1 -1/-1/-1 -1/-1/-1 -1/-1/-1 -1/1/-1 -1/1/-1 -1/1/-1 -1/1/-1 -1/1/-1 1/-1/-1 1/-1/-1 -1/-1/-1 -1/-1/-1 1/-1/-1 1/-1/-1 1/-1/-1 -1/-1/-1 16/-1/-1 -1/-1/-1 1/-1/-1 1/-1/-1 -1/-1/-1 -1/-1/-1 1/-1/-1 1/-1/-1 -1/-1/-1 -1/-1/-1 -1/-1/-1 -1/-1/-1 -1/-1/-1 -1/-1/-1 -1/-1/-1 -1/-1/-1 -1/-1/-1 
1/-1/-1 -1/-1/-1 -1/1/-1 -1/1/-1 -1/1/-1 -1/-1/-1 1/-1/-1 1/-1/-1 -1/-1/-1 -1/-1/-1 -1/-1/-1 1/-1/-1 1/-1/-1 1/-1/-1 1/-1/-1 1/-1/-1 1/-1/-1 -1/-1/-1 -1/-1/-1 1/-1/-1 1/-1/-1 -1/-1/-1 -1/-1/-1 2/-1/-1 -1/-1/-1 -1/-1/-1 1/-1/-1 1/-1/-1 -1/-1/-1 -1/1/-1 1/-1/-1 -1/-1/-1 -1/-1/-1 -1/-1/-1 -1/-1/-1 -1/-1/-1 -1/-1/-1 -1/-1/-1 -1/-1/-1 -1/-1/-1 
1/-1/-1 -1/-1/-1 -1/1/-1 -1/1/-1 -1/1/-1 -1/-1/-1 -1/-1/-1 1/-1/-1 1/-1/-1 -1/-1/-1 -1/-1/-1 -1/-1/-1 1/-1/-1 1/-1/-1 1/-1/-1 1/-1/-1 1/-1/-1 5/-1/-1 5/-1/-1 1/-1/-1 1/-1/-1 -1/-1/-1 -1/-1/-1 -1/-1/-1 -1/-1/-1 -1/-1/-1 1/-1/-1 1/-1/-1 1/-1/-1 -1/1/-1 1/-1/-1 1/-1/-1 1/-1/-1 1/-1/-1 1/-1/-1 1/-1/-1 1/-1/-1 1/-1/-1 -1/-1/-1 -1/-1/-1 
1/-1/-1 1/-1/-1 1/-1/-1 -1/1/-1 1/-1/-1 1/-1/-1 1/-1/-1 1/-1/-1 1/-1/-1 1/-1/-1 -1/-1/-1 -1/-1/-1 -1/-1/-1 -1/-1/-1 2/-1/-1 -1/-1/-1 -1/-1/-1 -1/-1/-1 -1/-1/-1 -1/-1/-1 -1/-1/-1 -1/-1/-1 -1/-1/-1 -1/-1/-1 -1/-1/-1 -1/-1/-1 -1/-1/-1 -1/-1/-1 -1/-1/-1 -1/-1/-1 -1/-1/-1 -1/-1/-1 -1/-1/-1 -1/-1/-1 -1/-1/-1 -1/-1/-1 2/-1/-1 1/-1/-1 -1/-1/-1 -1/-1/-1 
1/-1/-1 -1/3/-1 -1/3/-1 -1/3/-1 -1/3/-1 1/-1/-1 10/3/-1 1/-1/-1 -1/3/-1 1/-1/-1 1/-1/-1 -1/-1/-1 -1/-1/-1 -1/-1/-1 -1/-1/-1 -1/-1/-1 -1/-1/-1 -1/-1/-1 -1/-1/-1 -1/-1/-1 -1/-1/-1 -1/-1/-1 -1/-1/-1 -1/-1/-1 -1/-1/-1 -1/-1/-1 -1/-1/-1 -1/-1/-1 -1/-1/-1 -1/-1/-1 -1/-1/-1 -1/-1/-1 -1/-1/-1 -1/-1/-1 -1/-1/-1 -1/-1/-1 -1/-1/-1 1/-1/-1 -1/-1/-1 -1/-1/-1 
1/-1/-1 12/3/-1 1/-1/-1 1/-1/-1 12/3/-1 1/-1/-1 -1/3/-1 -1/3/-1 -1/3/-1 -1/3/-1 1/-1/-1 1/-1/-1 1/-1/-1 1/-1/-1 1/-1/-1 1/-1/-1 1/-1/-1 1/-1/-1 1/-1/-1 1/-1/-1 1/-1/-1 1/-1/-1 -1/-1/-1 -1/-1/-1 -1/-1/-1 1/-1/-1 1/-1/-1 1/-1/-1 1/-1/-1 1/-1/-1 1/-1/-1 1/-1/-1 1/-1/-1 1/-1/-1 1/-1/-1 -1/-1/-1 -1/-1/-1 1/-1/-1 -1/-1/-1 -1/-1/-1 
1/-1/-1 -1/3/-1 -1/3/-1 -1/3/-1 -1/3/-1 1/-1/-1 -1/3/-1 -1/3/-1 -1/3/-1 1/-1/-1 -1/3/-1 -1/3/-1 -1/3/-1 -1/3/-1 -1/3/-1 -1/3/-1 -1/3/-1 1/-1/-1 -1/3/-1 -1/3/-1 10/3/-1 1/-1/-1 -1/7/-1 -1/7/-1 -1/7/-1 1/-1/-1 -1/-1/-1 -1/-1/-1 -1/-1/-1 -1/-1/-1 -1/-1/-1 -1/-1/-1 -1/-1/-1 -1/-1/-1 1/-1/-1 4/-1/-1 4/-1/-1 1/-1/-1 -1/-1/-1 -1/-1/-1 
1/-1/-1 -1/3/-1 -1/3/-1 1/-1/-1 1/-1/-1 1/-1/-1 1/-1/-1 1/-1/-1 -1/3/-1 1/-1/-1 -1/3/-1 1/-1/-1 1/-1/-1 12/3/-1 12/3/-1 1/-1/-1 11/3/-1 1/-1/-1 -1/3/-1 1/-1/-1 1/-1/-1 1/-1/-1 -1/7/-1 2/7/-1 -1/7/-1 1/-1/-1 -1/-1/-1 -1/-1/-1 -1/-1/-1 -1/-1/-1 -1/-1/-1 -1/-1/-1 -1/-1/-1 -1/-1/-1 1/-1/-1 -1/-1/-1 -1/-1/-1 1/-1/-1 -1/-1/-1 -1/-1/-1 
1/-1/-1 -1/3/-1 1/-1/-1 1/-1/-1 -1/3/-1 12/3/-1 -1/3/-1 -1/3/-1 -1/3/-1 11/3/-1 -1/3/-1 -1/3/-1 -1/3/-1 -1/3/-1 -1/3/-1 1/-1/-1 -1/3/-1 -1/3/-1 -1/3/-1 -1/-1/-1 -1/-1/-1 1/-1/-1 1/-1/-1 1/-1/-1 1/-1/-1 1/-1/-1 -1/-1/-1 -1/-1/-1 -1/-1/-1 -1/-1/-1 -1/-1/-1 -1/-1/-1 -1/-1/-1 -1/-1/-1 1/-1/-1 -1/-1/-1 -1/-1/-1 1/-1/-1 -1/-1/-1 -1/-1/-1 
1/-1/-1 -1/3/-1 -1/3/-1 -1/3/-1 -1/3/-1 1/-1/-1 -1/3/-1 -1/3/-1 -1/3/-1 11/3/-1 1/-1/-1 12/3/-1 1/-1/-1 1/-1/-1 -1/3/-1 1/-1/-1 -1/3/-1 -1/3/-1 1/-1/-1 -1/-1/-1 1/-1/-1 1/-1/-1 1/-1/-1 1/-1/-1 1/-1/-1 1/-1/-1 1/-1/-1 1/-1/-1 1/-1/-1 1/-1/-1 1/-1/-1 1/-1/-1 -1/-1/-1 -1/-1/-1 1/-1/-1 5/-1/-1 5/-1/-1 1/-1/-1 -1/-1/-1 -1/-1/-1 
1/-1/-1 1/-1/-1 -1/3/-1 1/-1/-1 1/-1/-1 1/-1/-1 11/3/-1 1/-1/-1 1/-1/-1 1/-1/-1 1/-1/-1 -1/3/-1 -1/3/-1 -1/3/-1 -1/3/-1 12/3/-1 -1/3/-1 1/-1/-1 1/-1/-1 -1/7/-1 1/-1/-1 -1/7/-1 -1/7/-1 -1/7/-1 -1/7/-1 -1/7/-1 -1/7/-1 -1/7/-1 -1/7/-1 -1/7/-1 -1/7/-1 1/-1/-1 -1/-1/-1 -1/-1/-1 1/-1/-1 -1/-1/-1 -1/-1/-1 1/-1/-1 -1/-1/-1 -1/-1/-1 
1/-1/-1 1/-1/-1 -1/3/-1 1/-1/-1 -1/1/-1 -1/1/-1 -1/3/-1 -1/3/-1 -1/3/-1 -1/3/-1 1/-1/-1 -1/3/-1 1/-1/-1 1/-1/-1 1/-1/-1 1/-1/-1 1/-1/-1 1/-1/-1 1/-1/-1 1/-1/-1 1/-1/-1 -1/-1/-1 -1/-1/-1 2/-1/-1 -1/-1/-1 -1/-1/-1 -1/-1/-1 2/-1/-1 -1/-1/-1 -1/-1/-1 -1/-1/-1 1/-1/-1 1/-1/-1 1/-1/-1 1/-1/-1 -1/-1/-1 -1/-1/-1 1/-1/-1 -1/-1/-1 -1/-1/-1 
1/-1/-1 -1/-1/-1 -1/3/-1 1/-1/-1 -1/1/-1 1/-1/-1 -1/3/-1 -1/3/-1 -1/3/-1 -1/3/-1 11/3/-1 -1/3/-1 -1/3/-1 1/-1/-1 -1/-1/-1 -1/-1/-1 -1/-1/-1 5/-1/-1 -1/-1/-1 -1/-1/-1 -1/-1/-1 -1/-1/-1 -1/-1/-1 5/-1/-1 -1/-1/-1 -1/-1/-1 -1/-1/-1 5/-1/-1 -1/-1/-1 -1/-1/-1 -1/-1/-1 -1/-1/-1 -1/-1/-1 -1/-1/-1 -1/-1/-1 -1/-1/-1 -1/-1/-1 1/-1/-1 -1/-1/-1 -1/-1/-1 
1/-1/-1 -1/-1/-1 1/-1/-1 1/-1/-1 -1/-1/-1 1/-1/-1 -1/3/-1 1/-1/-1 11/3/-1 1/-1/-1 1/-1/-1 1/-1/-1 12/3/-1 1/-1/-1 -1/-1/-1 -1/-1/-1 -1/-1/-1 -1/-1/-1 -1/-1/-1 -1/-1/-1 -1/-1/-1 -1/-1/-1 -1/-1/-1 -1/-1/-1 -1/-1/-1 -1/-1/-1 -1/-1/-1 -1/-1/-1 -1/-1/-1 -1/-1/-1 -1/-1/-1 -1/-1/-1 -1/-1/-1 -1/-1/-1 -1/-1/-1 -1/-1/-1 -1/-1/-1 1/-1/-1 -1/-1/-1 -1/-1/-1 
1/-1/-1 -1/7/-1 1/-1/-1 1/-1/-1 11/-1/-1 1/-1/-1 1/-1/-1 1/-1/-1 -1/3/-1 1/-1/-1 -1/3/-1 1/-1/-1 -1/3/-1 -1/3/-1 -1/-1/-1 -1/-1/-1 -1/-1/-1 -1/-1/-1 -1/-1/-1 -1/-1/-1 -1/-1/-1 -1/-1/-1 -1/-1/-1 -1/-1/-1 -1/-1/-1 -1/-1/-1 -1/-1/-1 -1/-1/-1 -1/-1/-1 -1/-1/-1 -1/-1/-1 -1/-1/-1 -1/-1/-1 -1/-1/-1 1/-1/-1 -1/3/-1 -1/3/-1 1/-1/-1 -1/-1/-1 -1/-1/-1 
1/-1/-1 1/-1/-1 1/-1/-1 1/-1/-1 -1/-1/-1 1/-1/-1 -1/3/-1 -1/3/-1 -1/3/-1 -1/3/-1 -1/3/-1 -1/3/-1 -1/3/-1 -1/3/-1 -1/-1/-1 8/-1/-1 -1/-1/-1 -1/-1/-1 -1/-1/-1 -1/-1/-1 -1/-1/-1 5/-1/-1 -1/-1/-1 -1/-1/-1 -1/-1/-1 5/-1/-1 -1/-1/-1 -1/-1/-1 -1/-1/-1 5/-1/-1 -1/-1/-1 -1/-1/-1 8/-1/-1 -1/-1/-1 1/-1/-1 -1/3/-1 -1/3/-1 1/-1/-1 -1/-1/-1 -1/-1/-1 
1/-1/-1 1/-1/-1 1/-1/-1 1/-1/-1 -1/-1/-1 1/-1/-1 1/-1/-1 1/-1/-1 1/-1/-1 1/-1/-1 1/-1/-1 1/-1/-1 1/-1/-1 1/-1/-1 1/-1/-1 1/-1/-1 1/-1/-1 1/-1/-1 1/-1/-1 1/-1/-1 1/-1/-1 -1/-1/-1 -1/-1/-1 -1/-1/-1 -1/-1/-1 2/-1/-1 -1/-1/-1 -1/-1/-1 -1/-1/-1 -1/-1/-1 -1/-1/-1 1/-1/-1 1/-1/-1 1/-1/-1 1/-1/-1 1/-1/-1 1/-1/-1 1/-1/-1 1/-1/-1 1/-1/-1 
1/-1/-1 -1/7/-1 1/-1/-1 -1/-1/-1 -1/-1/-1 -1/-1/-1 1/-1/-1 -1/-1/-1 1/-1/-1 6/-1/-1 -1/-1/-1 -1/-1/-1 -1/-1/-1 -1/-1/-1 -1/-1/-1 -1/-1/-1 -1/-1/-1 -1/-1/-1 -1/-1/-1 -1/-1/-1 1/-1/-1 -1/7/-1 -1/7/-1 -1/7/-1 -1/7/-1 -1/7/-1 -1/7/-1 -1/7/-1 -1/7/-1 -1/7/-1 -1/7/-1 1/-1/-1 -1/-1/-1 -1/-1/-1 -1/-1/-1 -1/-1/-1 -1/-1/-1 -1/-1/-1 -1/-1/-1 1/-1/-1 
1/-1/-1 -1/-1/-1 1/-1/-1 -1/-1/-1 2/-1/-1 -1/-1/-1 1/-1/-1 1/-1/-1 1/-1/-1 1/-1/-1 12/-1/-1 1/-1/-1 -1/-1/-1 -1/-1/-1 -1/-1/-1 -1/-1/-1 -1/-1/-1 -1/-1/-1 2/-1/-1 -1/-1/-1 1/-1/-1 1/-1/-1 1/-1/-1 1/-1/-1 1/-1/-1 1/-1/-1 1/-1/-1 1/-1/-1 1/-1/-1 1/-1/-1 1/-1/-1 1/-1/-1 -1/-1/-1 2/-1/-1 -1/-1/-1 -1/-1/-1 -1/-1/-1 2/-1/-1 -1/-1/-1 1/-1/-1 
1/-1/-1 -1/1/-1 -1/1/-1 -1/-1/-1 -1/-1/-1 -1/-1/-1 -1/-1/-1 -1/-1/-1 1/-1/-1 -1/-1/-1 -1/-1/-1 -1/-1/-1 -1/-1/-1 -1/-1/-1 -1/-1/-1 -1/-1/-1 -1/-1/-1 -1/-1/-1 -1/-1/-1 -1/-1/-1 -1/-1/-1 -1/-1/-1 12/-1/-1 -1/-1/-1 -1/-1/-1 -1/-1/-1 11/-1/-1 -1/-1/-1 -1/-1/-1 -1/-1/-1 12/-1/-1 -1/-1/-1 -1/-1/-1 -1/-1/-1 -1/-1/-1 -1/-1/-1 -1/-1/-1 -1/-1/-1 -1/-1/-1 1/-1/-1 
1/-1/-1 4/-1/-1 1/-1/-1 1/-1/-1 1/-1/-1 1/-1/-1 1/-1/-1 -1/-1/-1 1/-1/-1 -1/-1/-1 2/-1/-1 -1/-1/-1 -1/-1/-1 -1/-1/-1 -1/-1/-1 -1/-1/-1 -1/-1/-1 -1/-1/-1 -1/-1/-1 -1/-1/-1 10/-1/-1 -1/-1/-1 12/-1/-1 -1/-1/-1 10/-1/-1 -1/-1/-1 11/-1/-1 -1/-1/-1 10/-1/-1 -1/-1/-1 12/-1/-1 -1/-1/-1 10/-1/-1 -1/-1/-1 -1/-1/-1 -1/-1/-1 -1/-1/-1 -1/-1/-1 -1/-1/-1 1/-1/-1 
1/-1/-1 4/-1/-1 1/-1/-1 -1/-1/-1 -1/-1/-1 -1/-1/-1 1/-1/-1 -1/-1/-1 1/-1/-1 -1/-1/-1 -1/-1/-1 -1/-1/-1 -1/-1/-1 -1/-1/-1 -1/-1/-1 -1/-1/-1 -1/-1/-1 -1/-1/-1 -1/-1/-1 -1/-1/-1 -1/-1/-1 -1/-1/-1 12/-1/-1 -1/-1/-1 -1/-1/-1 -1/-1/-1 11/-1/-1 -1/-1/-1 -1/-1/-1 -1/-1/-1 12/-1/-1 -1/-1/-1 -1/-1/-1 -1/-1/-1 -1/-1/-1 -1/-1/-1 -1/-1/-1 4/-1/-1 -1/-1/-1 1/-1/-1 
1/-1/-1 4/-1/-1 1/-1/-1 -1/-1/-1 -1/-1/-1 -1/-1/-1 1/-1/-1 -1/-1/-1 1/-1/-1 -1/-1/-1 -1/-1/-1 -1/-1/-1 4/-1/-1 1/-1/-1 1/-1/-1 1/-1/-1 1/-1/-1 1/-1/-1 1/-1/-1 1/-1/-1 1/-1/-1 1/-1/-1 1/-1/-1 1/-1/-1 1/-1/-1 1/-1/-1 1/-1/-1 1/-1/-1 1/-1/-1 1/-1/-1 1/-1/-1 1/-1/-1 1/-1/-1 1/-1/-1 1/-1/-1 1/-1/-1 -1/-1/-1 -1/-1/-1 -1/-1/-1 1/-1/-1 
1/-1/-1 4/-1/-1 1/-1/-1 -1/-1/-1 -1/-1/-1 -1/-1/-1 1/-1/-1 -1/-1/-1 1/-1/-1 -1/7/-1 -1/7/-1 -1/7/-1 -1/7/-1 1/-1/-1 -1/7/-1 -1/7/-1 -1/7/-1 -1/7/-1 -1/7/-1 -1/7/-1 -1/7/-1 -1/7/-1 -1/7/-1 -1/7/-1 -1/7/-1 -1/7/-1 -1/7/-1 -1/7/-1 -1/7/-1 -1/7/-1 -1/7/-1 -1/7/-1 -1/7/-1 1/-1/-1 -1/-1/-1 1/-1/-1 -1/-1/-1 -1/-1/-1 -1/-1/-1 1/-1/-1 
1/-1/-1 4/-1/-1 1/-1/-1 -1/-1/-1 -1/-1/-1 -1/-1/-1 1/-1/-1 -1/-1/-1 1/-1/-1 -1/7/-1 -1/7/-1 -1/7/-1 -1/7/-1 1/-1/-1 2/-1/-1 -1/-1/-1 -1/-1/-1 2/-1/-1 -1/-1/-1 -1/-1/-1 2/-1/-1 -1/-1/-1 -1/-1/-1 2/-1/-1 -1/-1/-1 -1/-1/-1 2/-1/-1 -1/-1/-1 -1/-1/-1 2/-1/-1 -1/-1/-1 -1/-1/-1 2/-1/-1 1/-1/-1 -1/-1/-1 1/-1/-1 -1/-1/-1 -1/-1/-1 -1/-1/-1 1/-1/-1 
1/-1/-1 -1/-1/-1 1/-1/-1 1/-1/-1 1/-1/-1 1/-1/-1 1/-1/-1 -1/-1/-1 1/-1/-1 2/7/-1 -1/7/-1 -1/7/-1 2/7/-1 1/-1/-1 -1/-1/-1 -1/-1/-1 -1/-1/-1 -1/-1/-1 -1/-1/-1 -1/-1/-1 -1/-1/-1 -1/-1/-1 -1/-1/-1 -1/-1/-1 -1/-1/-1 -1/-1/-1 -1/-1/-1 -1/-1/-1 -1/-1/-1 -1/-1/-1 -1/-1/-1 -1/-1/-1 -1/-1/-1 1/-1/-1 -1/-1/-1 1/-1/-1 -1/-1/-1 -1/-1/-1 -1/-1/-1 1/-1/-1 
1/-1/-1 -1/-1/-1 -1/-1/-1 -1/-1/-1 -1/-1/-1 -1/-1/-1 1/-1/-1 -1/-1/-1 1/-1/-1 1/-1/-1 1/-1/-1 1/-1/-1 1/-1/-1 1/-1/-1 -1/-1/-1 -1/-1/-1 -1/-1/-1 -1/-1/-1 -1/-1/-1 -1/-1/-1 -1/-1/-1 -1/-1/-1 -1/-1/-1 -1/-1/-1 -1/-1/-1 -1/-1/-1 -1/-1/-1 -1/-1/-1 -1/-1/-1 -1/-1/-1 -1/-1/-1 -1/-1/-1 -1/-1/-1 1/-1/-1 1/-1/-1 1/-1/-1 -1/-1/-1 4/-1/-1 -1/-1/-1 1/-1/-1 
1/-1/-1 -1/-1/-1 -1/-1/-1 -1/-1/-1 -1/-1/-1 -1/-1/-1 1/-1/-1 -1/-1/-1 -1/-1/-1 -1/-1/-1 -1/-1/-1 -1/-1/-1 -1/-1/-1 -1/-1/-1 -1/-1/-1 -1/-1/-1 -1/-1/-1 -1/-1/-1 -1/-1/-1 -1/-1/-1 -1/-1/-1 -1/-1/-1 -1/-1/-1 10/-1/-1 -1/-1/-1 -1/-1/-1 -1/-1/-1 -1/-1/-1 -1/-1/-1 -1/-1/-1 -1/-1/-1 -1/-1/-1 -1/-1/-1 -1/-1/-1 -1/-1/-1 -1/-1/-1 -1/-1/-1 -1/-1/-1 -1/-1/-1 1/-1/-1 
1/-1/-1 1/-1/-1 1/-1/-1 1/-1/-1 -1/1/-1 -1/1/-1 1/-1/-1 -1/-1/-1 -1/-1/-1 -1/-1/-1 -1/-1/-1 -1/-1/-1 -1/-1/-1 -1/-1/-1 -1/-1/-1 -1/-1/-1 -1/-1/-1 -1/-1/-1 -1/-1/-1 -1/-1/-1 -1/-1/-1 -1/-1/-1 -1/-1/-1 -1/-1/-1 -1/-1/-1 -1/-1/-1 -1/-1/-1 -1/-1/-1 -1/-1/-1 -1/-1/-1 -1/-1/-1 -1/-1/-1 -1/-1/-1 -1/-1/-1 -1/-1/-1 -1/-1/-1 -1/-1/-1 -1/-1/-1 -1/-1/-1 1/-1/-1 
-1/-1/-1 -1/-1/-1 -1/-1/-1 1/-1/-1 -1/1/-1 -1/1/-1 -1/1/-1 -1/-1/-1 -1/-1/-1 -1/-1/-1 8/-1/-1 -1/-1/-1 -1/-1/-1 -1/-1/-1 -1/-1/-1 -1/-1/-1 -1/-1/-1 -1/-1/-1 -1/-1/-1 -1/-1/-1 -1/-1/-1 -1/-1/-1 -1/-1/-1 -1/-1/-1 -1/-1/-1 -1/-1/-1 -1/-1/-1 -1/-1/-1 -1/-1/-1 -1/-1/-1 -1/-1/-1 -1/-1/-1 -1/-1/-1 -1/-1/-1 -1/-1/-1 -1/-1/-1 -1/-1/-1 -1/-1/-1 -1/-1/-1 1/-1/-1 
-1/-1/-1 -1/-1/-1 -1/-1/-1 1/-1/-1 1/-1/-1 1/-1/-1 1/-1/-1 1/-1/-1 1/-1/-1 1/-1/-1 1/-1/-1 1/-1/-1 1/-1/-1 1/-1/-1 12/-1/-1 12/-1/-1 12/-1/-1 12/-1/-1 12/-1/-1 12/-1/-1 12/-1/-1 11/-1/-1 11/-1/-1 11/-1/-1 11/-1/-1 11/-1/-1 12/-1/-1 12/-1/-1 12/-1/-1 12/-1/-1 12/-1/-1 12/-1/-1 12/-1/-1 1/-1/-1 1/-1/-1 1/-1/-1 1/-1/-1 1/-1/-1 1/-1/-1 1/-1/-1 
-1/-1/-1 -1/-1/-1 -1/-1/-1 -1/-1/-1 -1/-1/-1 1/-1/-1 2/-1/-1 -1/-1/-1 -1/-1/-1 -1/-1/-1 -1/-1/-1 -1/-1/-1 -1/-1/-1 -1/1/-1 -1/-1/-1 -1/-1/-1 -1/-1/-1 2/-1/-1 -1/-1/-1 -1/-1/-1 -1/-1/-1 -1/-1/-1 -1/-1/-1 2/-1/-1 -1/-1/-1 -1/-1/-1 -1/-1/-1 -1/-1/-1 -1/-1/-1 2/-1/-1 -1/-1/-1 -1/-1/-1 -1/-1/-1 1/-1/-1 -1/-1/-1 -1/-1/-1 -1/-1/-1 -1/-1/-1 -1/-1/-1 -1/-1/-1 
-1/-1/-1 -1/-1/-1 -1/-1/-1 -1/-1/-1 -1/-1/-1 1/-1/-1 -1/-1/-1 -1/-1/-1 -1/-1/-1 -1/-1/-1 -1/-1/-1 -1/-1/-1 -1/-1/-1 1/-1/-1 -1/-1/-1 -1/-1/-1 -1/-1/-1 -1/-1/-1 -1/-1/-1 -1/-1/-1 -1/-1/-1 -1/-1/-1 -1/-1/-1 -1/-1/-1 -1/-1/-1 -1/-1/-1 -1/-1/-1 -1/-1/-1 -1/-1/-1 -1/-1/-1 -1/-1/-1 -1/-1/-1 -1/-1/-1 1/-1/-1 -1/-1/-1 -1/-1/-1 -1/-1/-1 -1/-1/-1 -1/-1/-1 -1/-1/-1 
-1/-1/-1 -1/-1/-1 -1/-1/-1 -1/-1/-1 -1/-1/-1 1/-1/-1 1/-1/-1 1/-1/-1 1/-1/-1 1/-1/-1 1/-1/-1 1/-1/-1 1/-1/-1 1/-1/-1 -1/7/-1 -1/7/-1 -1/7/-1 -1/7/-1 -1/7/-1 -1/7/-1 -1/7/-1 -1/7/-1 -1/7/-1 -1/7/-1 -1/7/-1 -1/7/-1 -1/7/-1 -1/7/-1 -1/7/-1 -1/7/-1 -1/7/-1 -1/7/-1 -1/7/-1 1/-1/-1 -1/-1/-1 -1/-1/-1 -1/-1/-1 -1/-1/-1 -1/-1/-1 -1/-1/-1 
-1/-1/-1 -1/-1/-1 -1/-1/-1 -1/-1/-1 -1/-1/-1 -1/-1/-1 -1/-1/-1 -1/-1/-1 -1/-1/-1 -1/-1/-1 -1/-1/-1 -1/-1/-1 -1/-1/-1 1/-1/-1 1/-1/-1 1/-1/-1 1/-1/-1 1/-1/-1 1/-1/-1 1/-1/-1 1/-1/-1 1/-1/-1 1/-1/-1 1/-1/-1 1/-1/-1 1/-1/-1 1/-1/-1 1/-1/-1 1/-1/-1 1/-1/-1 1/-1/-1 1/-1/-1 1/-1/-1 1/-1/-1 -1/-1/-1 -1/-1/-1 -1/-1/-1 -1/-1/-1 -1/-1/-1 -1/-1/-1 
</content>
    <position>3 4</position>
    <gravity>1</gravity>
    <official />
    <next-map>Stage 3</next-map>
  </map>
  <map>
    <name>Stage 1</name>
    <width>20</width>
    <height>15</height>
    <content>
1/-1/-1 1/-1/-1 1/-1/-1 1/-1/-1 1/-1/-1 1/-1/-1 1/-1/-1 1/-1/-1 1/-1/-1 1/-1/-1 1/-1/-1 1/-1/-1 1/-1/-1 1/-1/-1 1/-1/-1 1/-1/-1 1/-1/-1 1/-1/-1 1/-1/-1 1/-1/-1 
1/-1/-1 -1/-1/-1 2/-1/-1 -1/-1/-1 -1/3/-1 -1/3/-1 -1/3/-1 -1/3/-1 -1/7/-1 -1/7/-1 -1/7/-1 -1/7/-1 -1/7/-1 -1/7/-1 -1/7/-1 -1/7/-1 -1/7/-1 -1/7/-1 -1/7/-1 1/-1/-1 
1/-1/-1 -1/-1/-1 -1/-1/-1 -1/-1/-1 -1/3/-1 -1/3/-1 -1/3/-1 -1/3/-1 -1/7/-1 -1/7/-1 -1/7/-1 -1/7/-1 -1/7/-1 -1/7/-1 -1/7/-1 -1/7/-1 -1/7/-1 -1/7/-1 -1/7/-1 1/-1/-1 
1/-1/-1 1/-1/-1 1/-1/-1 1/-1/-1 -1/7/-1 -1/7/-1 -1/7/-1 -1/3/-1 -1/7/-1 -1/7/-1 -1/7/-1 -1/7/-1 -1/7/-1 -1/7/-1 -1/7/-1 -1/7/-1 2/7/-1 -1/7/-1 -1/7/-1 1/-1/-1 
1/-1/-1 -1/7/-1 -1/7/-1 -1/7/-1 -1/7/-1 -1/7/-1 -1/7/-1 -1/3/-1 -1/7/-1 -1/3/-1 -1/3/-1 -1/3/-1 -1/3/-1 -1/7/-1 1/-1/-1 1/-1/-1 1/-1/-1 1/-1/-1 1/-1/-1 1/-1/-1 
1/-1/-1 -1/7/-1 -1/7/-1 -1/7/-1 -1/7/-1 -1/7/-1 -1/7/-1 -1/-1/-1 -1/7/-1 -1/3/-1 -1/3/-1 -1/3/-1 -1/3/-1 -1/3/-1 -1/-1/-1 -1/-1/-1 6/-1/-1 -1/-1/-1 -1/-1/-1 1/-1/-1 
1/-1/-1 -1/7/-1 -1/7/-1 -1/7/-1 -1/7/-1 -1/7/-1 -1/7/-1 -1/-1/-1 -1/7/-1 -1/-1/-1 -1/7/-1 -1/7/-1 -1/7/-1 -1/7/-1 -1/7/-1 -1/7/-1 -1/7/-1 -1/7/-1 -1/7/-1 1/-1/-1 
1/-1/-1 -1/7/-1 -1/7/-1 -1/7/-1 -1/7/-1 -1/3/-1 -1/3/-1 -1/3/-1 -1/7/-1 2/-1/-1 -1/7/-1 -1/7/-1 -1/7/-1 -1/7/-1 -1/7/-1 -1/7/-1 -1/7/-1 -1/7/-1 -1/7/-1 1/-1/-1 
1/-1/-1 -1/7/-1 -1/7/-1 -1/3/-1 -1/3/-1 -1/3/-1 -1/3/-1 -1/3/-1 -1/7/-1 -1/-1/-1 -1/7/-1 -1/7/-1 -1/7/-1 -1/7/-1 -1/7/-1 -1/7/-1 -1/7/-1 -1/7/-1 -1/7/-1 1/-1/-1 
1/-1/-1 -1/7/-1 -1/7/-1 -1/3/-1 -1/7/-1 -1/7/-1 -1/7/-1 -1/7/-1 -1/7/-1 5/3/-1 -1/7/-1 -1/7/-1 -1/7/-1 -1/7/-1 -1/7/-1 -1/7/-1 -1/7/-1 -1/7/-1 -1/7/-1 1/-1/-1 
1/-1/-1 -1/7/-1 -1/7/-1 -1/3/-1 -1/7/-1 -1/7/-1 -1/7/-1 -1/7/-1 -1/7/-1 -1/3/-1 -1/7/-1 -1/7/-1 -1/7/-1 -1/7/-1 -1/7/-1 -1/7/-1 -1/7/-1 -1/7/-1 -1/7/-1 1/-1/-1 
1/-1/-1 -1/7/-1 -1/7/-1 2/3/-1 -1/3/-1 -1/3/-1 -1/3/-1 -1/3/-1 -1/3/-1 -1/3/-1 -1/7/-1 -1/7/-1 -1/7/-1 -1/7/-1 -1/7/-1 -1/7/-1 2/7/-1 -1/7/-1 -1/7/-1 1/-1/-1 
1/-1/-1 -1/7/-1 -1/7/-1 -1/3/-1 -1/3/-1 -1/3/-1 -1/3/-1 -1/3/-1 -1/3/-1 -1/3/-1 -1/7/-1 -1/7/-1 -1/7/-1 -1/7/-1 -1/7/-1 -1/7/-1 -1/7/-1 -1/7/-1 -1/7/-1 1/-1/-1 
1/-1/-1 -1/7/-1 -1/7/-1 -1/7/-1 -1/7/-1 -1/7/-1 -1/7/-1 -1/7/-1 -1/7/-1 -1/7/-1 -1/7/-1 -1/7/-1 -1/7/-1 -1/7/-1 -1/7/-1 -1/7/-1 -1/7/-1 -1/7/-1 -1/7/-1 1/-1/-1 
1/-1/-1 1/-1/-1 1/-1/-1 1/-1/-1 1/-1/-1 1/-1/-1 1/-1/-1 1/-1/-1 1/-1/-1 1/-1/-1 1/-1/-1 1/-1/-1 1/-1/-1 1/-1/-1 1/-1/-1 1/-1/-1 1/-1/-1 1/-1/-1 1/-1/-1 1/-1/-1 
</content>
    <position>2 2</position>
    <gravity>1</gravity>
    <official />
    <next-map>Stage 2</next-map>
  </map>
  <map>
    <name>map13</name>
    <width>19</width>
    <height>15</height>
    <content>
-1/-1/-1 -1/-1/-1 -1/-1/-1 -1/-1/-1 -1/-1/-1 -1/-1/-1 -1/-1/-1 -1/-1/-1 -1/-1/-1 -1/-1/-1 -1/-1/-1 -1/-1/-1 -1/-1/-1 -1/-1/-1 -1/-1/-1 -1/-1/-1 -1/-1/-1 -1/-1/-1 -1/-1/-1 
-1/-1/-1 -1/-1/-1 -1/-1/-1 -1/-1/-1 1/-1/-1 -1/-1/-1 1/-1/-1 -1/-1/-1 1/-1/-1 -1/-1/-1 1/-1/-1 -1/-1/-1 1/-1/-1 -1/-1/-1 1/-1/-1 -1/-1/-1 1/-1/-1 -1/-1/-1 -1/-1/-1 
-1/-1/-1 1/-1/-1 16/-1/-1 -1/-1/-1 16/-1/-1 -1/-1/-1 16/-1/-1 -1/-1/-1 16/-1/-1 -1/-1/-1 16/-1/-1 -1/-1/-1 16/-1/-1 -1/-1/-1 16/-1/-1 -1/-1/-1 16/-1/-1 -1/-1/-1 -1/-1/-1 
-1/-1/-1 -1/-1/-1 -1/-1/-1 -1/-1/-1 -1/-1/-1 -1/-1/-1 -1/-1/-1 -1/-1/-1 -1/-1/-1 -1/-1/-1 -1/-1/-1 -1/-1/-1 -1/-1/-1 -1/-1/-1 -1/-1/-1 -1/-1/-1 -1/-1/-1 -1/-1/-1 -1/-1/-1 
-1/-1/-1 1/-1/-1 16/-1/-1 -1/-1/-1 -1/-1/-1 -1/-1/-1 -1/-1/-1 -1/-1/-1 -1/-1/-1 -1/-1/-1 -1/-1/-1 -1/-1/-1 -1/-1/-1 -1/-1/-1 -1/-1/-1 -1/-1/-1 16/-1/-1 1/-1/-1 -1/-1/-1 
-1/-1/-1 -1/-1/-1 -1/-1/-1 -1/-1/-1 -1/-1/-1 -1/-1/-1 -1/-1/-1 -1/-1/-1 -1/-1/-1 -1/-1/-1 -1/-1/-1 -1/-1/-1 -1/-1/-1 -1/-1/-1 -1/-1/-1 -1/-1/-1 -1/-1/-1 -1/-1/-1 -1/-1/-1 
-1/-1/-1 1/-1/-1 16/-1/-1 -1/-1/-1 -1/-1/-1 -1/-1/-1 -1/-1/-1 -1/-1/-1 -1/-1/-1 -1/-1/-1 -1/-1/-1 -1/-1/-1 -1/-1/-1 -1/-1/-1 -1/-1/-1 -1/-1/-1 16/-1/-1 1/-1/-1 -1/-1/-1 
-1/-1/-1 -1/-1/-1 -1/-1/-1 -1/-1/-1 -1/-1/-1 -1/-1/-1 -1/-1/-1 -1/-1/-1 -1/-1/-1 -1/-1/-1 -1/-1/-1 -1/-1/-1 -1/-1/-1 -1/-1/-1 -1/-1/-1 -1/-1/-1 -1/-1/-1 -1/-1/-1 -1/-1/-1 
-1/-1/-1 1/-1/-1 16/-1/-1 -1/-1/-1 -1/-1/-1 -1/-1/-1 -1/-1/-1 -1/-1/-1 -1/-1/-1 -1/-1/-1 -1/-1/-1 -1/-1/-1 -1/-1/-1 -1/-1/-1 -1/-1/-1 -1/-1/-1 16/-1/-1 1/-1/-1 -1/-1/-1 
-1/-1/-1 -1/-1/-1 -1/-1/-1 -1/-1/-1 -1/-1/-1 -1/-1/-1 -1/-1/-1 -1/-1/-1 -1/-1/-1 -1/-1/-1 -1/-1/-1 -1/-1/-1 -1/-1/-1 -1/-1/-1 -1/-1/-1 -1/-1/-1 -1/-1/-1 -1/-1/-1 -1/-1/-1 
-1/-1/-1 1/-1/-1 16/-1/-1 -1/-1/-1 -1/-1/-1 -1/-1/-1 -1/-1/-1 -1/-1/-1 -1/-1/-1 -1/-1/-1 -1/-1/-1 -1/-1/-1 -1/-1/-1 -1/-1/-1 -1/-1/-1 -1/-1/-1 16/-1/-1 1/-1/-1 -1/-1/-1 
-1/-1/-1 -1/-1/-1 -1/-1/-1 -1/-1/-1 -1/-1/-1 -1/-1/-1 -1/-1/-1 -1/-1/-1 -1/-1/-1 -1/-1/-1 -1/-1/-1 -1/-1/-1 -1/-1/-1 -1/-1/-1 -1/-1/-1 -1/-1/-1 -1/-1/-1 -1/-1/-1 -1/-1/-1 
-1/-1/-1 -1/-1/-1 16/-1/-1 -1/-1/-1 16/-1/-1 -1/-1/-1 16/-1/-1 -1/-1/-1 16/-1/-1 -1/-1/-1 16/-1/-1 -1/-1/-1 16/-1/-1 -1/-1/-1 16/-1/-1 -1/-1/-1 16/-1/-1 1/-1/-1 -1/-1/-1 
-1/-1/-1 -1/-1/-1 1/-1/-1 -1/-1/-1 1/-1/-1 -1/-1/-1 1/-1/-1 -1/-1/-1 1/-1/-1 -1/-1/-1 1/-1/-1 -1/-1/-1 1/-1/-1 -1/-1/-1 1/-1/-1 -1/-1/-1 -1/-1/-1 -1/-1/-1 -1/-1/-1 
-1/-1/-1 -1/-1/-1 -1/-1/-1 -1/-1/-1 -1/-1/-1 -1/-1/-1 -1/-1/-1 -1/-1/-1 -1/-1/-1 -1/-1/-1 -1/-1/-1 -1/-1/-1 -1/-1/-1 -1/-1/-1 -1/-1/-1 -1/-1/-1 -1/-1/-1 -1/-1/-1 -1/-1/-1 
</content>
    <position>9 7</position>
    <gravity>1</gravity>
    <next-map>map13</next-map>
  </map>
  <map>
    <name>Stage 4</name>
    <width>30</width>
    <height>30</height>
    <content>
-1/-1/-1 -1/-1/-1 -1/-1/-1 -1/-1/-1 -1/-1/-1 -1/-1/-1 -1/-1/-1 -1/-1/-1 -1/-1/-1 -1/-1/-1 -1/-1/-1 -1/-1/-1 -1/-1/-1 -1/-1/-1 -1/-1/-1 -1/-1/-1 -1/-1/-1 -1/-1/-1 -1/-1/-1 -1/-1/-1 -1/-1/-1 -1/-1/-1 -1/-1/-1 -1/-1/-1 -1/-1/-1 -1/-1/-1 -1/-1/-1 -1/-1/-1 -1/-1/-1 -1/-1/-1 
-1/-1/-1 1/-1/-1 1/-1/-1 1/-1/-1 1/-1/-1 1/-1/-1 1/-1/-1 1/-1/-1 1/-1/-1 1/-1/-1 1/-1/-1 -1/-1/-1 -1/-1/-1 -1/-1/-1 -1/-1/-1 -1/-1/-1 -1/-1/-1 -1/-1/-1 -1/-1/-1 -1/-1/-1 -1/-1/-1 -1/-1/-1 -1/-1/-1 -1/-1/-1 -1/-1/-1 -1/-1/-1 -1/-1/-1 -1/-1/-1 -1/-1/-1 -1/-1/-1 
-1/-1/-1 1/-1/-1 -1/-1/-1 -1/-1/-1 -1/-1/-1 -1/-1/-1 -1/-1/-1 -1/-1/-1 -1/-1/-1 -1/-1/-1 1/-1/-1 -1/-1/-1 -1/-1/-1 -1/-1/-1 -1/-1/-1 -1/-1/-1 -1/-1/-1 -1/-1/-1 -1/-1/-1 -1/-1/-1 -1/-1/-1 -1/-1/-1 -1/-1/-1 -1/-1/-1 -1/-1/-1 -1/-1/-1 -1/-1/-1 -1/-1/-1 -1/-1/-1 -1/-1/-1 
-1/-1/-1 1/-1/-1 -1/-1/-1 -1/-1/-1 2/-1/-1 -1/-1/-1 -1/-1/-1 -1/-1/-1 6/-1/-1 -1/-1/-1 1/-1/-1 -1/-1/-1 -1/-1/-1 -1/-1/-1 -1/-1/-1 -1/-1/-1 -1/-1/-1 -1/-1/-1 -1/-1/-1 -1/-1/-1 -1/-1/-1 -1/-1/-1 -1/-1/-1 -1/-1/-1 -1/-1/-1 -1/-1/-1 -1/-1/-1 -1/-1/-1 -1/-1/-1 -1/-1/-1 
-1/-1/-1 1/-1/-1 -1/-1/-1 -1/-1/-1 -1/-1/-1 -1/-1/-1 -1/-1/-1 -1/-1/-1 -1/-1/-1 -1/-1/-1 1/-1/-1 -1/-1/-1 -1/-1/-1 -1/-1/-1 -1/-1/-1 -1/-1/-1 -1/-1/-1 -1/-1/-1 -1/-1/-1 -1/-1/-1 -1/-1/-1 -1/-1/-1 -1/-1/-1 -1/-1/-1 -1/-1/-1 -1/-1/-1 -1/-1/-1 -1/-1/-1 -1/-1/-1 -1/-1/-1 
-1/-1/-1 1/-1/-1 -1/-1/-1 -1/-1/-1 -1/-1/-1 -1/-1/-1 -1/-1/-1 1/-1/-1 1/-1/-1 1/-1/-1 1/-1/-1 -1/-1/-1 -1/-1/-1 -1/-1/-1 -1/-1/-1 -1/-1/-1 -1/-1/-1 -1/-1/-1 -1/-1/-1 -1/-1/-1 -1/-1/-1 -1/-1/-1 -1/-1/-1 -1/-1/-1 -1/-1/-1 -1/-1/-1 -1/-1/-1 -1/-1/-1 -1/-1/-1 -1/-1/-1 
-1/-1/-1 1/-1/-1 -1/-1/-1 -1/-1/-1 -1/-1/-1 -1/-1/-1 -1/-1/-1 1/-1/-1 -1/-1/-1 -1/-1/-1 -1/-1/-1 -1/-1/-1 -1/-1/-1 -1/-1/-1 -1/-1/-1 -1/-1/-1 -1/-1/-1 -1/-1/-1 -1/-1/-1 -1/-1/-1 -1/-1/-1 -1/-1/-1 -1/-1/-1 -1/-1/-1 -1/-1/-1 -1/-1/-1 -1/-1/-1 -1/-1/-1 -1/-1/-1 -1/-1/-1 
-1/-1/-1 1/-1/-1 -1/-1/-1 -1/-1/-1 -1/-1/-1 -1/-1/-1 14/-1/-1 1/-1/-1 1/-1/-1 1/-1/-1 1/-1/-1 1/-1/-1 -1/-1/-1 -1/-1/-1 -1/-1/-1 -1/-1/-1 -1/-1/-1 -1/-1/-1 -1/-1/-1 -1/-1/-1 -1/-1/-1 -1/-1/-1 -1/-1/-1 -1/-1/-1 -1/-1/-1 -1/-1/-1 -1/-1/-1 -1/-1/-1 -1/-1/-1 -1/-1/-1 
-1/-1/-1 1/-1/-1 14/-1/-1 -1/-1/-1 -1/-1/-1 -1/-1/-1 -1/-1/-1 -1/1/-1 -1/-1/-1 -1/-1/-1 -1/-1/-1 1/-1/-1 1/-1/-1 1/-1/-1 1/-1/-1 1/-1/-1 1/-1/-1 1/-1/-1 1/-1/-1 1/-1/-1 1/-1/-1 1/-1/-1 1/-1/-1 1/-1/-1 1/-1/-1 1/-1/-1 1/-1/-1 1/-1/-1 1/-1/-1 1/-1/-1 
-1/-1/-1 1/-1/-1 12/-1/-1 -1/-1/-1 -1/-1/-1 -1/-1/-1 -1/-1/-1 1/-1/-1 -1/-1/-1 10/-1/-1 -1/-1/-1 1/-1/-1 -1/-1/-1 1/-1/-1 -1/7/-1 -1/7/-1 -1/7/-1 -1/7/-1 -1/7/-1 -1/7/-1 -1/7/-1 -1/7/-1 -1/7/-1 1/-1/-1 2/-1/-1 -1/-1/-1 -1/-1/-1 -1/-1/-1 -1/1/-1 1/-1/-1 
-1/-1/-1 1/-1/-1 4/-1/-1 -1/-1/-1 -1/-1/-1 -1/-1/-1 -1/-1/-1 1/-1/-1 -1/-1/-1 -1/-1/-1 -1/-1/-1 1/-1/-1 -1/-1/-1 1/-1/-1 -1/-1/-1 2/-1/-1 -1/-1/-1 -1/-1/-1 2/-1/-1 -1/-1/-1 -1/-1/-1 2/-1/-1 -1/-1/-1 1/-1/-1 -1/-1/-1 -1/-1/-1 -1/-1/-1 -1/-1/-1 -1/1/-1 1/-1/-1 
-1/-1/-1 1/-1/-1 1/-1/-1 1/-1/-1 1/-1/-1 1/-1/-1 11/-1/-1 1/-1/-1 1/-1/-1 1/-1/-1 1/-1/-1 1/-1/-1 1/-1/-1 1/-1/-1 -1/-1/-1 -1/-1/-1 -1/-1/-1 -1/-1/-1 -1/-1/-1 -1/-1/-1 -1/-1/-1 -1/-1/-1 -1/-1/-1 1/-1/-1 1/-1/-1 1/-1/-1 1/-1/-1 1/-1/-1 -1/1/-1 1/-1/-1 
-1/-1/-1 1/-1/-1 -1/-1/-1 1/-1/-1 2/-1/-1 -1/-1/-1 -1/-1/-1 -1/-1/-1 -1/-1/-1 -1/-1/-1 -1/-1/-1 -1/-1/-1 -1/-1/-1 -1/-1/-1 -1/-1/-1 -1/-1/-1 -1/-1/-1 -1/-1/-1 -1/-1/-1 -1/-1/-1 -1/-1/-1 -1/-1/-1 -1/-1/-1 -1/-1/-1 -1/-1/-1 -1/-1/-1 -1/-1/-1 -1/-1/-1 2/-1/-1 1/-1/-1 
-1/-1/-1 1/-1/-1 10/-1/-1 1/-1/-1 -1/-1/-1 -1/-1/-1 -1/-1/-1 -1/-1/-1 -1/-1/-1 -1/-1/-1 -1/-1/-1 -1/-1/-1 -1/-1/-1 -1/-1/-1 -1/-1/-1 4/-1/-1 -1/-1/-1 4/-1/-1 -1/-1/-1 4/-1/-1 -1/-1/-1 4/-1/-1 -1/-1/-1 -1/-1/-1 8/-1/-1 -1/-1/-1 -1/-1/-1 -1/-1/-1 -1/-1/-1 1/-1/-1 
-1/-1/-1 1/-1/-1 -1/-1/-1 1/-1/-1 -1/-1/-1 1/-1/-1 1/-1/-1 1/-1/-1 1/-1/-1 -1/-1/-1 1/-1/-1 1/-1/-1 1/-1/-1 1/-1/-1 1/-1/-1 1/-1/-1 1/-1/-1 1/-1/-1 1/-1/-1 1/-1/-1 1/-1/-1 1/-1/-1 1/-1/-1 1/-1/-1 1/-1/-1 1/-1/-1 4/-1/-1 1/-1/-1 1/-1/-1 1/-1/-1 
-1/-1/-1 1/-1/-1 -1/-1/-1 1/-1/-1 -1/-1/-1 1/-1/-1 1/-1/-1 1/-1/-1 -1/-1/-1 -1/-1/-1 1/-1/-1 1/-1/-1 -1/-1/-1 -1/-1/-1 -1/-1/-1 -1/-1/-1 -1/-1/-1 -1/-1/-1 -1/-1/-1 -1/-1/-1 -1/-1/-1 -1/-1/-1 -1/-1/-1 -1/-1/-1 -1/-1/-1 1/-1/-1 4/-1/-1 1/-1/-1 -1/-1/-1 -1/-1/-1 
-1/-1/-1 1/-1/-1 -1/-1/-1 1/-1/-1 -1/-1/-1 1/-1/-1 1/-1/-1 -1/-1/-1 -1/-1/-1 1/-1/-1 1/-1/-1 -1/-1/-1 -1/-1/-1 2/-1/-1 -1/-1/-1 -1/-1/-1 -1/-1/-1 -1/-1/-1 -1/-1/-1 -1/-1/-1 -1/-1/-1 -1/-1/-1 2/-1/-1 -1/-1/-1 -1/-1/-1 -1/-1/-1 4/-1/-1 1/-1/-1 -1/-1/-1 -1/-1/-1 
-1/-1/-1 1/-1/-1 -1/-1/-1 1/-1/-1 -1/-1/-1 1/-1/-1 -1/-1/-1 -1/-1/-1 1/-1/-1 1/-1/-1 -1/-1/-1 -1/-1/-1 -1/-1/-1 -1/-1/-1 -1/-1/-1 -1/-1/-1 -1/-1/-1 -1/-1/-1 -1/-1/-1 -1/-1/-1 -1/-1/-1 -1/-1/-1 -1/-1/-1 -1/-1/-1 -1/-1/-1 -1/-1/-1 4/-1/-1 1/-1/-1 -1/-1/-1 -1/-1/-1 
-1/-1/-1 1/-1/-1 13/-1/-1 1/-1/-1 -1/-1/-1 -1/-1/-1 -1/-1/-1 1/-1/-1 1/-1/-1 -1/-1/-1 -1/-1/-1 -1/-1/-1 -1/-1/-1 -1/-1/-1 -1/-1/-1 -1/-1/-1 -1/-1/-1 -1/-1/-1 -1/-1/-1 -1/-1/-1 -1/-1/-1 -1/-1/-1 -1/-1/-1 1/-1/-1 1/-1/-1 1/-1/-1 1/-1/-1 1/-1/-1 -1/-1/-1 -1/-1/-1 
-1/-1/-1 1/-1/-1 1/-1/-1 1/-1/-1 13/-1/-1 -1/-1/-1 1/-1/-1 1/-1/-1 -1/-1/-1 -1/-1/-1 -1/-1/-1 -1/-1/-1 11/-1/-1 -1/-1/-1 -1/-1/-1 -1/-1/-1 -1/-1/-1 -1/-1/-1 -1/-1/-1 -1/-1/-1 -1/-1/-1 -1/-1/-1 -1/-1/-1 1/-1/-1 -1/-1/-1 -1/-1/-1 -1/-1/-1 -1/-1/-1 -1/-1/-1 -1/-1/-1 
1/-1/-1 1/-1/-1 1/-1/-1 1/-1/-1 1/-1/-1 1/-1/-1 1/-1/-1 -1/-1/-1 -1/-1/-1 -1/-1/-1 -1/-1/-1 -1/-1/-1 -1/-1/-1 -1/-1/-1 -1/-1/-1 -1/-1/-1 -1/-1/-1 -1/-1/-1 -1/-1/-1 -1/-1/-1 -1/-1/-1 -1/-1/-1 -1/-1/-1 1/-1/-1 -1/-1/-1 -1/-1/-1 -1/-1/-1 -1/-1/-1 -1/-1/-1 -1/-1/-1 
1/-1/-1 2/-1/-1 -1/-1/-1 -1/-1/-1 16/-1/-1 1/-1/-1 -1/-1/-1 -1/-1/-1 -1/-1/-1 -1/-1/-1 -1/-1/-1 11/-1/-1 -1/-1/-1 -1/-1/-1 -1/-1/-1 -1/-1/-1 -1/-1/-1 -1/-1/-1 -1/-1/-1 -1/-1/-1 -1/-1/-1 -1/-1/-1 -1/-1/-1 1/-1/-1 -1/-1/-1 -1/-1/-1 -1/-1/-1 -1/-1/-1 -1/-1/-1 -1/-1/-1 
1/-1/-1 -1/-1/-1 -1/-1/-1 10/-1/-1 -1/-1/-1 -1/-1/-1 -1/-1/-1 -1/-1/-1 -1/-1/-1 -1/-1/-1 -1/-1/-1 -1/-1/-1 -1/-1/-1 -1/-1/-1 -1/-1/-1 -1/-1/-1 -1/-1/-1 -1/-1/-1 -1/-1/-1 -1/-1/-1 -1/-1/-1 -1/-1/-1 -1/-1/-1 1/-1/-1 -1/-1/-1 -1/-1/-1 -1/-1/-1 -1/-1/-1 -1/-1/-1 -1/-1/-1 
1/-1/-1 -1/-1/-1 -1/-1/-1 -1/-1/-1 -1/-1/-1 -1/-1/-1 -1/-1/-1 -1/-1/-1 -1/-1/-1 -1/-1/-1 11/-1/-1 -1/-1/-1 -1/-1/-1 -1/-1/-1 13/-1/-1 -1/-1/-1 -1/-1/-1 -1/-1/-1 -1/-1/-1 -1/-1/-1 -1/-1/-1 -1/-1/-1 -1/-1/-1 1/-1/-1 -1/-1/-1 -1/-1/-1 -1/-1/-1 -1/-1/-1 -1/-1/-1 -1/-1/-1 
1/-1/-1 1/-1/-1 1/-1/-1 1/-1/-1 1/-1/-1 1/-1/-1 1/-1/-1 1/-1/-1 1/-1/-1 1/-1/-1 1/-1/-1 1/-1/-1 1/-1/-1 1/-1/-1 1/-1/-1 1/-1/-1 1/-1/-1 -1/-1/-1 -1/-1/-1 -1/-1/-1 -1/-1/-1 -1/-1/-1 13/-1/-1 1/-1/-1 -1/-1/-1 -1/-1/-1 -1/-1/-1 -1/-1/-1 -1/-1/-1 -1/-1/-1 
1/-1/-1 -1/-1/-1 2/-1/-1 -1/-1/-1 1/-1/-1 1/-1/-1 1/-1/-1 -1/-1/-1 -1/-1/-1 -1/-1/-1 -1/-1/-1 2/-1/-1 -1/-1/-1 -1/-1/-1 -1/-1/-1 -1/-1/-1 1/-1/-1 1/-1/-1 -1/-1/-1 -1/-1/-1 1/-1/-1 1/-1/-1 1/-1/-1 1/-1/-1 1/-1/-1 1/-1/-1 1/-1/-1 1/-1/-1 1/-1/-1 1/-1/-1 
1/-1/-1 -1/-1/-1 -1/-1/-1 -1/-1/-1 11/-1/-1 14/-1/-1 11/-1/-1 -1/-1/-1 -1/-1/-1 -1/-1/-1 -1/-1/-1 -1/-1/-1 -1/-1/-1 -1/-1/-1 -1/-1/-1 -1/-1/-1 -1/-1/-1 1/-1/-1 14/-1/-1 1/-1/-1 1/-1/-1 -1/-1/-1 1/-1/-1 2/-1/-1 -1/-1/-1 -1/-1/-1 -1/-1/-1 -1/-1/-1 -1/-1/-1 1/-1/-1 
1/-1/-1 -1/-1/-1 -1/-1/-1 -1/-1/-1 11/-1/-1 11/-1/-1 11/-1/-1 -1/-1/-1 -1/-1/-1 -1/-1/-1 -1/-1/-1 -1/-1/-1 -1/-1/-1 -1/-1/-1 -1/-1/-1 -1/-1/-1 -1/-1/-1 -1/7/-1 -1/7/-1 -1/7/-1 1/-1/-1 1/-1/-1 1/-1/-1 -1/-1/-1 -1/-1/-1 -1/-1/-1 10/-1/-1 -1/-1/-1 -1/-1/-1 1/-1/-1 
1/-1/-1 -1/-1/-1 -1/-1/-1 -1/-1/-1 -1/-1/-1 -1/-1/-1 -1/-1/-1 -1/-1/-1 -1/-1/-1 -1/-1/-1 -1/-1/-1 -1/-1/-1 -1/-1/-1 -1/-1/-1 -1/-1/-1 -1/-1/-1 -1/-1/-1 -1/-1/-1 -1/-1/-1 -1/-1/-1 -1/1/-1 -1/1/-1 -1/1/-1 -1/-1/-1 -1/-1/-1 -1/-1/-1 -1/-1/-1 -1/-1/-1 -1/-1/-1 1/-1/-1 
1/-1/-1 1/-1/-1 1/-1/-1 1/-1/-1 1/-1/-1 1/-1/-1 1/-1/-1 1/-1/-1 1/-1/-1 1/-1/-1 1/-1/-1 1/-1/-1 1/-1/-1 1/-1/-1 1/-1/-1 1/-1/-1 1/-1/-1 1/-1/-1 1/-1/-1 1/-1/-1 1/-1/-1 1/-1/-1 1/-1/-1 1/-1/-1 1/-1/-1 1/-1/-1 1/-1/-1 1/-1/-1 1/-1/-1 1/-1/-1 
</content>
    <position>2 28</position>
    <gravity>1</gravity>
    <official />
    <next-map>Stage 1</next-map>
  </map>-->
  <!--<map>
    <name>Stage 3</name>
    <width>40</width>
    <height>30</height>
    <content>
1/-1/-1 1/-1/-1 1/-1/-1 1/-1/-1 1/-1/-1 1/-1/-1 1/-1/-1 1/-1/-1 1/-1/-1 1/-1/-1 1/-1/-1 1/-1/-1 1/-1/-1 1/-1/-1 1/-1/-1 1/-1/-1 1/-1/-1 1/-1/-1 1/-1/-1 1/-1/-1 1/-1/-1 1/-1/-1 1/-1/-1 1/-1/-1 1/-1/-1 1/-1/-1 1/-1/-1 1/-1/-1 1/-1/-1 1/-1/-1 1/-1/-1 1/-1/-1 1/-1/-1 1/-1/-1 1/-1/-1 1/-1/-1 1/-1/-1 1/-1/-1 1/-1/-1 1/-1/-1 
1/-1/-1 -1/-1/-1 1/-1/-1 -1/3/-1 -1/3/-1 -1/3/-1 -1/-1/-1 -1/-1/-1 -1/-1/-1 6/-1/-1 1/-1/-1 -1/-1/-1 -1/-1/-1 -1/-1/-1 -1/-1/-1 -1/-1/-1 -1/-1/-1 -1/-1/-1 -1/-1/-1 -1/-1/-1 -1/-1/-1 -1/-1/-1 -1/-1/-1 -1/-1/-1 -1/-1/-1 -1/-1/-1 -1/-1/-1 1/-1/-1 1/-1/-1 1/-1/-1 1/-1/-1 1/-1/-1 -1/-1/-1 -1/-1/-1 -1/-1/-1 -1/-1/-1 -1/-1/-1 -1/-1/-1 -1/-1/-1 1/-1/-1 
1/-1/-1 -1/-1/-1 1/-1/-1 -1/3/-1 -1/3/-1 -1/3/-1 -1/-1/-1 -1/-1/-1 -1/-1/-1 -1/-1/-1 1/-1/-1 -1/-1/-1 -1/-1/-1 -1/-1/-1 -1/-1/-1 -1/-1/-1 -1/-1/-1 -1/-1/-1 -1/-1/-1 -1/-1/-1 -1/-1/-1 -1/-1/-1 -1/-1/-1 -1/-1/-1 -1/-1/-1 -1/-1/-1 -1/-1/-1 1/-1/-1 1/-1/-1 5/-1/-1 1/-1/-1 1/-1/-1 -1/-1/-1 -1/-1/-1 -1/-1/-1 -1/-1/-1 -1/-1/-1 -1/-1/-1 -1/-1/-1 1/-1/-1 
1/-1/-1 -1/-1/-1 1/-1/-1 -1/3/-1 -1/3/-1 1/-1/-1 1/-1/-1 1/-1/-1 1/-1/-1 1/-1/-1 1/-1/-1 1/-1/-1 1/-1/-1 1/-1/-1 1/-1/-1 1/-1/-1 1/-1/-1 1/-1/-1 1/-1/-1 1/-1/-1 1/-1/-1 1/-1/-1 1/-1/-1 1/-1/-1 1/-1/-1 -1/-1/-1 -1/-1/-1 1/-1/-1 1/-1/-1 10/-1/-1 1/-1/-1 1/-1/-1 -1/-1/-1 -1/-1/-1 -1/-1/-1 -1/-1/-1 -1/-1/-1 -1/-1/-1 -1/-1/-1 1/-1/-1 
1/-1/-1 -1/-1/-1 1/-1/-1 -1/3/-1 -1/3/-1 1/-1/-1 -1/-1/-1 -1/-1/-1 -1/-1/-1 -1/-1/-1 1/-1/-1 -1/7/-1 -1/7/-1 -1/7/-1 -1/7/-1 -1/7/-1 -1/7/-1 -1/7/-1 -1/7/-1 -1/7/-1 -1/7/-1 -1/7/-1 -1/7/-1 -1/7/-1 1/-1/-1 -1/-1/-1 -1/-1/-1 1/-1/-1 1/-1/-1 -1/-1/-1 1/-1/-1 1/-1/-1 -1/-1/-1 -1/-1/-1 -1/-1/-1 -1/-1/-1 -1/-1/-1 -1/-1/-1 -1/-1/-1 1/-1/-1 
1/-1/-1 -1/-1/-1 1/-1/-1 -1/-1/-1 -1/-1/-1 1/-1/-1 1/-1/-1 1/-1/-1 1/-1/-1 1/-1/-1 1/-1/-1 12/-1/-1 11/-1/-1 12/-1/-1 11/-1/-1 12/-1/-1 11/-1/-1 12/-1/-1 11/-1/-1 12/-1/-1 11/-1/-1 12/-1/-1 11/-1/-1 12/-1/-1 1/-1/-1 1/-1/-1 1/-1/-1 1/-1/-1 1/-1/-1 -1/-1/-1 1/-1/-1 1/-1/-1 1/-1/-1 1/-1/-1 -1/-1/-1 -1/-1/-1 -1/-1/-1 -1/-1/-1 -1/-1/-1 1/-1/-1 
1/-1/-1 -1/-1/-1 1/-1/-1 -1/-1/-1 -1/-1/-1 -1/-1/-1 -1/-1/-1 -1/-1/-1 -1/-1/-1 -1/-1/-1 -1/-1/-1 -1/-1/-1 -1/-1/-1 -1/-1/-1 -1/-1/-1 -1/-1/-1 -1/-1/-1 -1/-1/-1 -1/-1/-1 -1/-1/-1 -1/-1/-1 -1/-1/-1 -1/-1/-1 -1/-1/-1 -1/-1/-1 -1/-1/-1 -1/-1/-1 12/-1/-1 -1/-1/-1 -1/-1/-1 -1/-1/-1 -1/-1/-1 -1/-1/-1 1/-1/-1 -1/-1/-1 -1/-1/-1 -1/-1/-1 -1/-1/-1 -1/-1/-1 1/-1/-1 
1/-1/-1 -1/-1/-1 1/-1/-1 -1/-1/-1 -1/-1/-1 -1/-1/-1 -1/-1/-1 -1/-1/-1 -1/-1/-1 -1/-1/-1 -1/-1/-1 2/-1/-1 -1/-1/-1 10/-1/-1 -1/-1/-1 2/-1/-1 -1/-1/-1 10/-1/-1 -1/-1/-1 2/-1/-1 -1/-1/-1 10/-1/-1 -1/-1/-1 2/-1/-1 -1/-1/-1 -1/-1/-1 2/-1/-1 12/-1/-1 -1/-1/-1 -1/-1/-1 -1/-1/-1 -1/-1/-1 -1/-1/-1 1/-1/-1 -1/-1/-1 -1/-1/-1 -1/-1/-1 -1/-1/-1 -1/-1/-1 1/-1/-1 
1/-1/-1 -1/-1/-1 1/-1/-1 -1/-1/-1 -1/-1/-1 -1/-1/-1 -1/-1/-1 -1/-1/-1 -1/-1/-1 -1/-1/-1 -1/-1/-1 -1/-1/-1 -1/-1/-1 -1/-1/-1 -1/-1/-1 -1/-1/-1 -1/-1/-1 -1/-1/-1 -1/-1/-1 -1/-1/-1 -1/-1/-1 -1/-1/-1 -1/-1/-1 -1/-1/-1 -1/-1/-1 -1/-1/-1 8/-1/-1 12/-1/-1 -1/-1/-1 -1/-1/-1 -1/-1/-1 -1/-1/-1 -1/-1/-1 1/-1/-1 -1/-1/-1 -1/-1/-1 -1/-1/-1 -1/-1/-1 -1/-1/-1 1/-1/-1 
1/-1/-1 -1/-1/-1 1/-1/-1 -1/-1/-1 1/-1/-1 1/-1/-1 11/-1/-1 1/-1/-1 1/-1/-1 1/-1/-1 1/-1/-1 11/-1/-1 12/-1/-1 11/-1/-1 12/-1/-1 11/-1/-1 12/-1/-1 11/-1/-1 12/-1/-1 11/-1/-1 12/-1/-1 11/-1/-1 12/-1/-1 11/-1/-1 1/-1/-1 1/-1/-1 1/-1/-1 1/-1/-1 1/-1/-1 11/-1/-1 1/-1/-1 1/-1/-1 -1/-1/-1 1/-1/-1 -1/-1/-1 -1/-1/-1 -1/-1/-1 -1/-1/-1 -1/-1/-1 1/-1/-1 
1/-1/-1 -1/-1/-1 1/-1/-1 13/-1/-1 1/-1/-1 1/-1/-1 -1/-1/-1 1/-1/-1 -1/-1/-1 -1/-1/-1 1/-1/-1 -1/7/-1 -1/7/-1 -1/7/-1 -1/7/-1 -1/7/-1 -1/7/-1 -1/7/-1 -1/7/-1 -1/7/-1 -1/7/-1 -1/7/-1 -1/7/-1 -1/7/-1 1/-1/-1 -1/-1/-1 -1/-1/-1 1/-1/-1 1/-1/-1 -1/-1/-1 1/-1/-1 1/-1/-1 -1/-1/-1 1/-1/-1 -1/-1/-1 -1/-1/-1 -1/-1/-1 -1/-1/-1 -1/-1/-1 1/-1/-1 
1/-1/-1 -1/-1/-1 1/-1/-1 1/-1/-1 1/-1/-1 1/-1/-1 -1/-1/-1 1/-1/-1 -1/-1/-1 -1/-1/-1 1/-1/-1 1/-1/-1 1/-1/-1 1/-1/-1 1/-1/-1 1/-1/-1 1/-1/-1 1/-1/-1 1/-1/-1 1/-1/-1 1/-1/-1 1/-1/-1 1/-1/-1 1/-1/-1 1/-1/-1 -1/-1/-1 -1/-1/-1 1/-1/-1 1/-1/-1 10/-1/-1 1/-1/-1 1/-1/-1 10/-1/-1 1/-1/-1 -1/-1/-1 -1/-1/-1 -1/-1/-1 -1/-1/-1 -1/-1/-1 1/-1/-1 
1/-1/-1 -1/-1/-1 -1/-1/-1 -1/-1/-1 -1/-1/-1 1/-1/-1 -1/-1/-1 1/-1/-1 -1/-1/-1 -1/-1/-1 -1/-1/-1 -1/-1/-1 -1/-1/-1 -1/-1/-1 -1/-1/-1 -1/-1/-1 -1/-1/-1 -1/-1/-1 -1/-1/-1 -1/-1/-1 -1/-1/-1 -1/-1/-1 -1/-1/-1 -1/-1/-1 -1/-1/-1 -1/-1/-1 -1/-1/-1 1/-1/-1 1/-1/-1 5/-1/-1 1/-1/-1 1/-1/-1 1/-1/-1 1/-1/-1 -1/-1/-1 -1/-1/-1 -1/-1/-1 -1/-1/-1 -1/-1/-1 1/-1/-1 
1/-1/-1 -1/-1/-1 -1/-1/-1 -1/-1/-1 -1/-1/-1 1/-1/-1 -1/-1/-1 1/-1/-1 -1/-1/-1 -1/-1/-1 -1/-1/-1 -1/-1/-1 -1/-1/-1 -1/-1/-1 -1/-1/-1 -1/-1/-1 -1/-1/-1 -1/-1/-1 -1/-1/-1 -1/-1/-1 -1/-1/-1 -1/-1/-1 -1/-1/-1 -1/-1/-1 -1/-1/-1 -1/-1/-1 -1/-1/-1 1/-1/-1 1/-1/-1 -1/-1/-1 1/-1/-1 1/-1/-1 -1/-1/-1 -1/-1/-1 -1/-1/-1 -1/-1/-1 -1/-1/-1 -1/-1/-1 -1/-1/-1 1/-1/-1 
1/-1/-1 -1/-1/-1 -1/-1/-1 -1/-1/-1 -1/-1/-1 1/-1/-1 -1/-1/-1 1/-1/-1 -1/-1/-1 -1/-1/-1 -1/-1/-1 -1/-1/-1 -1/-1/-1 -1/-1/-1 -1/-1/-1 -1/-1/-1 -1/-1/-1 -1/-1/-1 -1/-1/-1 -1/-1/-1 -1/-1/-1 -1/-1/-1 -1/-1/-1 -1/-1/-1 -1/-1/-1 -1/-1/-1 -1/-1/-1 1/-1/-1 1/-1/-1 -1/-1/-1 1/-1/-1 1/-1/-1 -1/-1/-1 -1/-1/-1 -1/-1/-1 -1/-1/-1 -1/-1/-1 -1/-1/-1 -1/-1/-1 1/-1/-1 
1/-1/-1 -1/-1/-1 -1/-1/-1 -1/-1/-1 -1/-1/-1 1/-1/-1 13/-1/-1 1/-1/-1 -1/-1/-1 -1/-1/-1 -1/-1/-1 -1/-1/-1 -1/-1/-1 -1/-1/-1 -1/-1/-1 -1/-1/-1 -1/-1/-1 -1/-1/-1 -1/-1/-1 -1/-1/-1 -1/-1/-1 -1/-1/-1 -1/-1/-1 -1/-1/-1 -1/-1/-1 -1/-1/-1 -1/-1/-1 1/-1/-1 1/-1/-1 13/-1/-1 1/-1/-1 1/-1/-1 -1/-1/-1 -1/-1/-1 -1/-1/-1 -1/-1/-1 -1/-1/-1 -1/-1/-1 -1/-1/-1 1/-1/-1 
1/-1/-1 -1/-1/-1 -1/-1/-1 -1/-1/-1 -1/-1/-1 1/-1/-1 1/-1/-1 1/-1/-1 -1/-1/-1 -1/-1/-1 -1/-1/-1 -1/-1/-1 -1/-1/-1 -1/-1/-1 -1/-1/-1 -1/-1/-1 -1/-1/-1 -1/-1/-1 -1/-1/-1 -1/-1/-1 -1/-1/-1 -1/-1/-1 -1/-1/-1 -1/-1/-1 -1/-1/-1 -1/-1/-1 -1/-1/-1 1/-1/-1 -1/-1/-1 -1/-1/-1 -1/-1/-1 1/-1/-1 -1/-1/-1 -1/-1/-1 -1/-1/-1 -1/-1/-1 -1/-1/-1 -1/-1/-1 -1/-1/-1 1/-1/-1 
1/-1/-1 -1/-1/-1 -1/-1/-1 -1/-1/-1 -1/-1/-1 -1/-1/-1 -1/-1/-1 -1/-1/-1 -1/-1/-1 -1/-1/-1 -1/-1/-1 -1/-1/-1 -1/-1/-1 -1/-1/-1 -1/-1/-1 -1/-1/-1 -1/-1/-1 -1/-1/-1 -1/-1/-1 -1/-1/-1 -1/-1/-1 -1/-1/-1 -1/-1/-1 -1/-1/-1 -1/-1/-1 -1/-1/-1 -1/-1/-1 1/-1/-1 -1/3/-1 -1/3/-1 -1/3/-1 1/-1/-1 -1/-1/-1 -1/-1/-1 -1/-1/-1 -1/-1/-1 -1/-1/-1 -1/-1/-1 -1/-1/-1 1/-1/-1 
1/-1/-1 1/-1/-1 1/-1/-1 1/-1/-1 1/-1/-1 1/-1/-1 1/-1/-1 1/-1/-1 1/-1/-1 1/-1/-1 1/-1/-1 1/-1/-1 1/-1/-1 1/-1/-1 1/-1/-1 1/-1/-1 1/-1/-1 1/-1/-1 1/-1/-1 1/-1/-1 1/-1/-1 1/-1/-1 1/-1/-1 1/-1/-1 1/-1/-1 1/-1/-1 1/-1/-1 1/-1/-1 -1/3/-1 -1/3/-1 -1/3/-1 1/-1/-1 1/-1/-1 1/-1/-1 1/-1/-1 1/-1/-1 1/-1/-1 1/-1/-1 1/-1/-1 1/-1/-1 
1/-1/-1 -1/-1/-1 -1/-1/-1 -1/-1/-1 -1/-1/-1 -1/-1/-1 -1/-1/-1 -1/7/-1 -1/7/-1 -1/7/-1 -1/-1/-1 13/-1/-1 -1/-1/-1 -1/7/-1 -1/7/-1 -1/7/-1 -1/-1/-1 13/-1/-1 -1/-1/-1 -1/-1/-1 -1/-1/-1 -1/-1/-1 -1/-1/-1 -1/-1/-1 1/-1/-1 -1/-1/-1 -1/-1/-1 1/-1/-1 1/-1/-1 1/-1/-1 1/-1/-1 1/-1/-1 1/-1/-1 -1/-1/-1 -1/-1/-1 -1/-1/-1 -1/-1/-1 -1/-1/-1 -1/-1/-1 -1/-1/-1 
1/-1/-1 -1/-1/-1 1/-1/-1 -1/-1/-1 -1/-1/-1 -1/-1/-1 -1/-1/-1 -1/7/-1 2/7/-1 -1/7/-1 -1/-1/-1 -1/-1/-1 -1/-1/-1 -1/7/-1 2/7/-1 -1/7/-1 -1/-1/-1 -1/-1/-1 -1/-1/-1 -1/-1/-1 -1/-1/-1 -1/-1/-1 -1/-1/-1 -1/-1/-1 1/-1/-1 -1/-1/-1 -1/-1/-1 -1/-1/-1 -1/-1/-1 -1/-1/-1 1/-1/-1 -1/7/-1 1/-1/-1 -1/-1/-1 -1/-1/-1 -1/-1/-1 -1/-1/-1 -1/-1/-1 -1/-1/-1 -1/-1/-1 
1/-1/-1 -1/-1/-1 -1/-1/-1 -1/-1/-1 -1/-1/-1 -1/-1/-1 -1/-1/-1 -1/7/-1 -1/7/-1 -1/7/-1 -1/-1/-1 -1/-1/-1 -1/-1/-1 -1/7/-1 -1/7/-1 -1/7/-1 -1/-1/-1 -1/-1/-1 -1/-1/-1 -1/-1/-1 -1/-1/-1 -1/-1/-1 -1/-1/-1 -1/-1/-1 1/-1/-1 -1/-1/-1 -1/-1/-1 -1/-1/-1 -1/-1/-1 -1/-1/-1 1/-1/-1 14/-1/-1 1/-1/-1 1/-1/-1 1/-1/-1 1/-1/-1 1/-1/-1 1/-1/-1 1/-1/-1 1/-1/-1 
1/-1/-1 4/-1/-1 1/-1/-1 1/-1/-1 -1/-1/-1 -1/-1/-1 -1/-1/-1 -1/7/-1 -1/7/-1 -1/7/-1 -1/-1/-1 -1/-1/-1 -1/-1/-1 -1/7/-1 -1/7/-1 -1/7/-1 -1/-1/-1 -1/-1/-1 -1/-1/-1 -1/-1/-1 -1/-1/-1 -1/-1/-1 -1/-1/-1 -1/-1/-1 1/-1/-1 -1/-1/-1 -1/-1/-1 2/-1/-1 -1/-1/-1 -1/-1/-1 1/-1/-1 -1/-1/-1 -1/1/-1 -1/-1/-1 -1/-1/-1 -1/-1/-1 -1/-1/-1 -1/-1/-1 -1/-1/-1 1/-1/-1 
1/-1/-1 -1/-1/-1 -1/-1/-1 -1/-1/-1 -1/-1/-1 -1/-1/-1 -1/-1/-1 -1/7/-1 -1/7/-1 -1/7/-1 -1/-1/-1 -1/-1/-1 -1/-1/-1 -1/7/-1 -1/7/-1 -1/7/-1 -1/-1/-1 -1/-1/-1 -1/-1/-1 -1/-1/-1 -1/-1/-1 -1/-1/-1 -1/-1/-1 -1/-1/-1 1/-1/-1 -1/-1/-1 -1/-1/-1 -1/-1/-1 -1/-1/-1 -1/-1/-1 1/-1/-1 -1/-1/-1 1/-1/-1 1/-1/-1 1/-1/-1 1/-1/-1 1/-1/-1 1/-1/-1 -1/-1/-1 1/-1/-1 
1/-1/-1 -1/-1/-1 1/-1/-1 1/-1/-1 1/-1/-1 -1/-1/-1 -1/-1/-1 -1/7/-1 -1/7/-1 -1/7/-1 -1/-1/-1 -1/-1/-1 -1/-1/-1 -1/7/-1 -1/7/-1 -1/7/-1 -1/-1/-1 -1/-1/-1 -1/-1/-1 -1/-1/-1 -1/-1/-1 -1/-1/-1 -1/-1/-1 -1/-1/-1 1/-1/-1 -1/-1/-1 -1/-1/-1 -1/-1/-1 -1/-1/-1 13/-1/-1 1/-1/-1 -1/-1/-1 1/-1/-1 -1/-1/-1 -1/-1/-1 -1/-1/-1 -1/-1/-1 1/-1/-1 -1/-1/-1 1/-1/-1 
1/-1/-1 4/-1/-1 -1/-1/-1 -1/-1/-1 -1/-1/-1 -1/-1/-1 -1/-1/-1 -1/7/-1 -1/7/-1 -1/7/-1 -1/-1/-1 -1/-1/-1 -1/-1/-1 -1/7/-1 -1/7/-1 -1/7/-1 -1/-1/-1 -1/-1/-1 -1/-1/-1 -1/-1/-1 -1/-1/-1 -1/-1/-1 -1/-1/-1 -1/-1/-1 1/-1/-1 -1/-1/-1 -1/-1/-1 -1/-1/-1 -1/-1/-1 -1/-1/-1 1/-1/-1 4/-1/-1 1/-1/-1 -1/-1/-1 -1/-1/-1 -1/-1/-1 -1/-1/-1 1/-1/-1 -1/-1/-1 1/-1/-1 
1/-1/-1 -1/-1/-1 -1/-1/-1 -1/-1/-1 -1/-1/-1 -1/-1/-1 -1/-1/-1 -1/7/-1 -1/7/-1 -1/7/-1 -1/-1/-1 -1/-1/-1 -1/-1/-1 -1/7/-1 -1/7/-1 -1/7/-1 -1/-1/-1 -1/-1/-1 -1/-1/-1 -1/-1/-1 -1/-1/-1 -1/-1/-1 -1/-1/-1 -1/-1/-1 1/-1/-1 1/-1/-1 14/-1/-1 1/-1/-1 1/-1/-1 1/-1/-1 1/-1/-1 -1/-1/-1 1/-1/-1 -1/-1/-1 -1/-1/-1 -1/-1/-1 -1/-1/-1 1/-1/-1 -1/-1/-1 1/-1/-1 
1/-1/-1 -1/-1/-1 -1/-1/-1 -1/-1/-1 -1/-1/-1 -1/-1/-1 -1/-1/-1 -1/7/-1 2/7/-1 -1/7/-1 -1/-1/-1 -1/-1/-1 -1/-1/-1 -1/7/-1 2/7/-1 -1/7/-1 -1/-1/-1 -1/-1/-1 -1/-1/-1 -1/-1/-1 -1/-1/-1 -1/-1/-1 -1/-1/-1 -1/-1/-1 -1/-1/-1 -1/-1/-1 -1/-1/-1 -1/-1/-1 -1/-1/-1 -1/-1/-1 1/-1/-1 -1/1/-1 1/-1/-1 -1/-1/-1 -1/-1/-1 -1/-1/-1 -1/-1/-1 1/-1/-1 -1/-1/-1 1/-1/-1 
1/-1/-1 4/-1/-1 -1/-1/-1 -1/-1/-1 -1/-1/-1 13/-1/-1 -1/-1/-1 -1/7/-1 -1/7/-1 -1/7/-1 -1/-1/-1 13/-1/-1 -1/-1/-1 -1/7/-1 -1/7/-1 -1/7/-1 -1/-1/-1 -1/-1/-1 -1/-1/-1 -1/-1/-1 -1/-1/-1 -1/-1/-1 -1/-1/-1 -1/-1/-1 -1/-1/-1 -1/-1/-1 -1/-1/-1 -1/-1/-1 -1/-1/-1 -1/-1/-1 -1/1/-1 -1/1/-1 1/-1/-1 -1/-1/-1 -1/-1/-1 -1/-1/-1 -1/-1/-1 1/-1/-1 13/-1/-1 1/-1/-1 
1/-1/-1 1/-1/-1 1/-1/-1 1/-1/-1 1/-1/-1 1/-1/-1 1/-1/-1 1/-1/-1 1/-1/-1 1/-1/-1 1/-1/-1 1/-1/-1 1/-1/-1 1/-1/-1 1/-1/-1 1/-1/-1 1/-1/-1 1/-1/-1 1/-1/-1 1/-1/-1 1/-1/-1 1/-1/-1 1/-1/-1 1/-1/-1 1/-1/-1 1/-1/-1 1/-1/-1 1/-1/-1 1/-1/-1 1/-1/-1 1/-1/-1 1/-1/-1 1/-1/-1 -1/-1/-1 -1/-1/-1 -1/-1/-1 -1/-1/-1 1/-1/-1 1/-1/-1 1/-1/-1 
</content>
    <position>3 28</position>
    <gravity>1</gravity>
    <official />
    <next-map>Stage 4</next-map>
  </map>-->
  <map>
    <name>1 - Basics</name>
    <width>35</width>
    <height>8</height>
    <content>
-1/-1/-1 -1/-1/-1 -1/-1/-1 -1/-1/-1 -1/-1/-1 -1/-1/-1 -1/-1/-1 -1/-1/-1 -1/-1/-1 -1/-1/-1 -1/-1/-1 -1/-1/-1 -1/-1/-1 -1/-1/-1 -1/-1/-1 -1/-1/-1 -1/-1/-1 -1/-1/-1 -1/-1/-1 1/-1/1 1/-1/-1 1/-1/-1 1/-1/-1 1/-1/-1 1/-1/-1 1/-1/-1 1/-1/-1 1/-1/-1 1/-1/-1 1/-1/-1 1/-1/-1 1/-1/-1 1/-1/-1 1/-1/-1 1/-1/-1 
1/-1/-1 1/-1/-1 1/-1/-1 1/-1/-1 1/-1/-1 1/-1/-1 1/-1/-1 1/-1/-1 1/-1/-1 1/-1/-1 1/-1/-1 1/-1/-1 1/-1/-1 1/-1/-1 1/-1/-1 1/-1/-1 1/-1/-1 1/-1/-1 1/-1/-1 1/-1/-1 -1/-1/-1 -1/-1/m4 -1/-1/m4 -1/-1/m4 -1/-1/-1 -1/-1/-1 -1/-1/-1 -1/-1/-1 -1/-1/-1 -1/-1/-1 -1/-1/-1 -1/-1/-1 -1/-1/-1 -1/-1/-1 1/-1/-1 
1/-1/-1 -1/-1/-1 -1/-1/-1 -1/-1/-1 -1/-1/-1 -1/-1/-1 -1/-1/-1 -1/-1/-1 -1/-1/-1 -1/-1/-1 -1/-1/-1 -1/-1/-1 -1/-1/-1 -1/-1/-1 -1/-1/-1 -1/-1/-1 -1/-1/-1 -1/-1/-1 -1/-1/-1 -1/-1/-1 -1/-1/-1 -1/-1/m4 -1/-1/m4 -1/-1/m4 -1/-1/-1 -1/-1/-1 -1/-1/-1 -1/-1/-1 -1/-1/-1 -1/-1/-1 -1/-1/-1 6/-1/-1 -1/-1/-1 2/-1/-1 1/-1/-1 
1/-1/-1 -1/-1/m0 -1/-1/m0 -1/-1/m0 -1/-1/m0 -1/-1/m0 -1/-1/-1 -1/-1/-1 -1/-1/m1 -1/-1/m1 -1/-1/m1 -1/-1/-1 -1/-1/m2 -1/-1/m2 -1/-1/m2 -1/-1/-1 -1/-1/m3 -1/-1/m3 -1/-1/m3 -1/-1/-1 -1/-1/-1 -1/-1/m4 -1/-1/m4 -1/-1/m4 -1/-1/-1 -1/-1/-1 -1/-1/-1 -1/-1/-1 -1/-1/-1 -1/-1/-1 -1/-1/-1 -1/-1/-1 -1/-1/-1 -1/-1/-1 1/-1/-1 
1/-1/-1 -1/-1/m0 -1/-1/m0 2/-1/m0 -1/-1/m0 -1/-1/m0 -1/-1/-1 -1/-1/-1 -1/-1/m1 2/-1/m1 -1/-1/m1 -1/-1/-1 -1/-1/m2 2/-1/m2 -1/-1/m2 -1/-1/-1 -1/-1/m3 -1/-1/m3 -1/-1/m3 -1/-1/m3 1/-1/-1 1/-1/-1 1/-1/-1 1/-1/-1 1/-1/-1 1/-1/-1 1/-1/-1 1/-1/-1 1/-1/-1 1/-1/-1 1/-1/-1 1/-1/-1 1/-1/-1 1/-1/-1 1/-1/-1 
1/-1/-1 -1/-1/m0 -1/-1/m0 -1/-1/m0 -1/-1/m0 -1/-1/m0 -1/-1/-1 -1/-1/-1 -1/-1/m1 -1/-1/m1 -1/-1/m1 -1/-1/-1 -1/-1/m2 -1/-1/m2 -1/-1/m2 -1/-1/-1 -1/-1/m3 -1/-1/m3 -1/-1/m3 -1/-1/m3 1/-1/-1 -1/-1/-1 -1/-1/-1 -1/-1/-1 -1/-1/-1 -1/-1/-1 -1/-1/-1 -1/-1/-1 -1/-1/-1 -1/-1/-1 -1/-1/-1 -1/-1/-1 -1/-1/-1 -1/-1/-1 -1/-1/-1 
1/-1/-1 -1/-1/m0 -1/-1/m0 -1/-1/m0 -1/-1/m0 -1/-1/m0 -1/-1/-1 -1/-1/-1 -1/-1/m1 -1/-1/m1 -1/-1/m1 -1/-1/-1 -1/-1/m2 -1/-1/m2 -1/-1/m2 -1/-1/-1 -1/-1/m3 -1/-1/m3 -1/-1/m3 -1/-1/m3 1/-1/-1 -1/-1/-1 -1/-1/-1 -1/-1/-1 -1/-1/-1 -1/-1/-1 -1/-1/-1 -1/-1/-1 -1/-1/-1 -1/-1/-1 -1/-1/-1 -1/-1/-1 -1/-1/-1 -1/-1/-1 -1/-1/-1 
1/-1/-1 1/-1/-1 1/-1/-1 1/-1/-1 1/-1/-1 1/-1/-1 1/-1/-1 1/-1/-1 1/-1/-1 1/-1/-1 1/-1/-1 1/-1/-1 1/-1/-1 1/-1/-1 1/-1/-1 1/-1/-1 1/-1/-1 1/-1/-1 1/-1/-1 1/-1/-1 1/-1/-1 -1/-1/-1 -1/-1/-1 -1/-1/-1 -1/-1/-1 -1/-1/-1 -1/-1/-1 -1/-1/-1 -1/-1/-1 -1/-1/-1 -1/-1/-1 -1/-1/-1 -1/-1/-1 -1/-1/-1 -1/-1/-1 
</content>
    <position>3 6</position>
    <gravity>1</gravity>
    <tutorial />
    <official />
    <messages>
      <message value="0">Hi there!
Let's learn how to play together...
Use ← and → to move</message>
      <message value="1">See that cliff over there?</message>
      <message value="2">You don't?</message>
      <message value="3">Now you should see it. Pretty anoying walking in the dark, right? That's why I put torches all over the place.
Jump over it, use ↑ or space to do it.</message>
      <message value="4">The goal of each level is to reach the red spiraly thing to your right.
Go on, that will be all for now...</message>
    </messages>
    <next-map>2 - Jump and gravity pads</next-map>
  </map>
  <map>
    <name>3 - Special blocks</name>
    <width>20</width>
    <height>30</height>
    <content>
-1/-1/-1 -1/-1/-1 -1/-1/-1 1/-1/-1 1/-1/-1 1/-1/-1 1/-1/-1 1/-1/-1 1/-1/-1 1/-1/-1 1/-1/-1 1/-1/-1 1/-1/-1 1/-1/-1 1/-1/-1 1/-1/-1 1/-1/-1 1/-1/-1 1/-1/-1 -1/-1/-1 
-1/-1/-1 -1/-1/-1 -1/-1/-1 1/-1/-1 2/-1/m1 -1/-1/m1 -1/-1/m1 -1/-1/-1 -1/-1/-1 -1/-1/-1 -1/-1/-1 -1/-1/-1 -1/-1/-1 -1/-1/-1 -1/-1/-1 -1/-1/-1 -1/-1/-1 2/-1/-1 1/-1/-1 -1/-1/-1 
-1/-1/-1 -1/-1/-1 -1/-1/-1 1/-1/-1 -1/-1/m1 10/-1/m1 -1/-1/m1 -1/-1/-1 -1/-1/-1 -1/-1/-1 -1/-1/-1 -1/-1/-1 -1/-1/-1 -1/-1/-1 -1/-1/-1 -1/-1/-1 -1/-1/-1 -1/-1/-1 1/-1/-1 -1/-1/-1 
1/-1/-1 1/-1/-1 1/-1/-1 1/-1/-1 1/-1/-1 1/-1/-1 1/-1/-1 12/-1/-1 12/-1/-1 12/-1/-1 1/-1/-1 1/-1/-1 1/-1/-1 1/-1/-1 1/-1/-1 11/-1/-1 11/-1/-1 11/-1/-1 1/-1/-1 -1/-1/-1 
1/-1/-1 -1/-1/-1 -1/-1/-1 -1/-1/-1 -1/-1/m-1 -1/-1/m0 -1/-1/m0 -1/-1/m0 -1/-1/m0 -1/-1/m0 11/-1/-1 -1/-1/-1 -1/-1/-1 2/-1/-1 -1/-1/-1 -1/-1/-1 -1/-1/-1 -1/-1/-1 1/-1/-1 -1/-1/-1 
1/-1/-1 -1/-1/-1 -1/-1/-1 -1/-1/-1 -1/-1/m0 -1/-1/m0 -1/-1/m0 -1/-1/m0 -1/-1/m0 -1/-1/m0 11/-1/-1 -1/-1/-1 -1/-1/-1 -1/-1/-1 -1/-1/-1 -1/-1/-1 -1/-1/-1 -1/-1/-1 1/-1/-1 -1/-1/-1 
1/-1/-1 1/-1/-1 1/-1/-1 1/-1/-1 1/-1/-1 1/-1/-1 1/-1/-1 1/-1/-1 1/-1/-1 1/-1/-1 1/-1/-1 1/-1/-1 -1/-1/-1 -1/-1/-1 -1/-1/-1 1/-1/-1 1/-1/-1 1/-1/-1 1/-1/-1 -1/-1/-1 
1/-1/-1 2/-1/-1 14/-1/-1 -1/-1/-1 -1/-1/-1 -1/-1/-1 -1/-1/-1 -1/-1/-1 -1/-1/-1 -1/-1/-1 -1/-1/-1 1/-1/-1 -1/-1/-1 -1/-1/-1 -1/-1/-1 1/-1/-1 -1/-1/-1 -1/-1/-1 -1/-1/-1 -1/-1/-1 
1/-1/-1 -1/-1/-1 -1/-1/-1 -1/-1/-1 -1/-1/-1 -1/-1/-1 -1/-1/-1 -1/-1/-1 -1/-1/-1 -1/-1/-1 -1/-1/-1 1/-1/-1 -1/-1/-1 -1/-1/-1 -1/-1/-1 1/-1/-1 -1/-1/-1 -1/-1/-1 -1/-1/-1 -1/-1/-1 
1/-1/-1 -1/-1/-1 -1/-1/-1 -1/-1/-1 -1/-1/-1 -1/-1/-1 -1/-1/-1 -1/-1/-1 -1/-1/-1 -1/-1/-1 -1/-1/-1 -1/-1/m2 -1/-1/m2 -1/-1/m2 -1/-1/m2 1/-1/-1 -1/-1/-1 -1/-1/-1 -1/-1/-1 -1/-1/-1 
1/-1/-1 1/-1/-1 -1/-1/-1 1/-1/-1 -1/-1/-1 -1/-1/-1 -1/-1/-1 2/-1/-1 -1/-1/-1 -1/-1/-1 -1/-1/-1 -1/-1/m2 -1/-1/m2 2/-1/m2 -1/-1/m2 1/-1/-1 -1/-1/-1 -1/-1/-1 -1/-1/-1 -1/-1/-1 
-1/-1/-1 1/-1/-1 -1/-1/-1 1/-1/-1 -1/-1/-1 -1/-1/-1 -1/-1/-1 -1/-1/-1 -1/-1/-1 -1/-1/-1 -1/-1/-1 -1/-1/m2 -1/-1/m2 -1/-1/m2 -1/-1/m2 1/-1/-1 -1/-1/-1 -1/-1/-1 -1/-1/-1 -1/-1/-1 
-1/-1/-1 1/-1/-1 -1/-1/-1 1/-1/-1 -1/-1/-1 -1/-1/-1 -1/-1/-1 -1/-1/-1 -1/-1/-1 -1/-1/-1 -1/-1/-1 1/-1/-1 1/-1/-1 1/-1/-1 1/-1/-1 1/-1/-1 1/-1/-1 1/-1/-1 1/-1/-1 1/-1/-1 
-1/-1/-1 1/-1/-1 -1/-1/-1 1/-1/-1 -1/-1/-1 -1/-1/-1 -1/-1/-1 -1/-1/-1 -1/-1/-1 -1/-1/-1 -1/-1/-1 1/-1/-1 2/-1/-1 -1/-1/-1 -1/-1/-1 -1/-1/-1 -1/-1/-1 -1/-1/-1 2/-1/-1 1/-1/-1 
-1/-1/-1 1/-1/-1 -1/-1/-1 1/-1/-1 -1/-1/-1 -1/-1/-1 -1/-1/-1 -1/-1/-1 -1/-1/-1 14/-1/-1 -1/-1/-1 1/-1/-1 -1/-1/m4 -1/-1/m4 -1/-1/m4 -1/-1/m4 -1/-1/m4 -1/-1/m4 -1/-1/m4 1/-1/-1 
-1/-1/-1 1/-1/-1 -1/-1/-1 1/-1/-1 1/-1/-1 1/-1/-1 1/-1/-1 1/-1/-1 1/-1/-1 1/-1/-1 1/-1/-1 1/-1/-1 -1/-1/m4 -1/-1/m4 -1/-1/m4 6/-1/m4 -1/-1/m4 -1/-1/m4 -1/-1/m4 1/-1/-1 
-1/-1/-1 1/-1/-1 -1/-1/-1 1/-1/-1 -1/-1/-1 -1/-1/-1 -1/-1/-1 -1/-1/-1 1/-1/-1 -1/-1/-1 -1/-1/-1 -1/-1/-1 -1/-1/m4 -1/-1/m4 -1/-1/m4 -1/-1/m4 -1/-1/m4 -1/-1/m4 -1/-1/m4 1/-1/-1 
-1/-1/-1 1/-1/-1 -1/-1/-1 1/-1/-1 -1/-1/-1 -1/-1/-1 -1/-1/-1 -1/-1/-1 1/-1/-1 -1/-1/-1 2/-1/-1 -1/-1/-1 -1/-1/m4 -1/-1/m4 -1/-1/m4 -1/-1/m4 -1/-1/m4 -1/-1/m4 -1/-1/m4 1/-1/-1 
-1/-1/-1 1/-1/-1 -1/-1/-1 1/-1/-1 -1/-1/-1 -1/-1/-1 -1/-1/-1 -1/-1/-1 1/-1/-1 -1/-1/-1 -1/-1/-1 -1/-1/-1 1/-1/-1 1/-1/-1 1/-1/-1 1/-1/-1 1/-1/-1 1/-1/-1 1/-1/-1 1/-1/-1 
-1/-1/-1 1/-1/-1 -1/-1/-1 1/-1/-1 1/-1/-1 1/-1/-1 1/-1/-1 1/-1/-1 1/-1/-1 -1/-1/-1 -1/-1/-1 -1/-1/-1 1/-1/-1 -1/-1/-1 -1/-1/-1 -1/-1/-1 -1/-1/-1 -1/-1/-1 -1/-1/-1 -1/-1/-1 
-1/-1/-1 1/-1/-1 -1/-1/-1 -1/-1/m3 -1/-1/m3 -1/-1/m3 -1/-1/m3 -1/-1/-1 -1/-1/-1 -1/-1/-1 -1/-1/-1 -1/-1/-1 1/-1/-1 -1/-1/-1 -1/-1/-1 -1/-1/-1 -1/-1/-1 -1/-1/-1 -1/-1/-1 -1/-1/-1 
-1/-1/-1 1/-1/-1 -1/-1/-1 -1/-1/m3 -1/-1/m3 -1/-1/m3 2/-1/m3 -1/-1/-1 -1/-1/-1 -1/-1/-1 -1/-1/-1 -1/-1/-1 1/-1/-1 -1/-1/-1 -1/-1/-1 -1/-1/-1 -1/-1/-1 -1/-1/-1 -1/-1/-1 -1/-1/-1 
-1/-1/-1 1/-1/-1 -1/-1/-1 -1/-1/m3 -1/-1/m3 -1/-1/m3 -1/-1/m3 -1/-1/-1 -1/-1/-1 -1/-1/-1 -1/-1/-1 13/-1/-1 1/-1/-1 -1/-1/-1 -1/-1/-1 -1/-1/-1 -1/-1/-1 -1/-1/-1 -1/-1/-1 -1/-1/-1 
-1/-1/-1 1/-1/-1 1/-1/-1 1/-1/-1 1/-1/-1 1/-1/-1 -1/-1/-1 1/-1/-1 1/-1/-1 1/-1/-1 1/-1/-1 1/-1/-1 1/-1/-1 -1/-1/-1 -1/-1/-1 -1/-1/-1 -1/-1/-1 -1/-1/-1 -1/-1/-1 -1/-1/-1 
-1/-1/-1 -1/-1/-1 -1/-1/-1 -1/-1/-1 -1/-1/-1 1/-1/-1 -1/-1/-1 1/-1/-1 -1/-1/-1 -1/-1/-1 -1/-1/-1 -1/-1/-1 -1/-1/-1 -1/-1/-1 -1/-1/-1 -1/-1/-1 -1/-1/-1 -1/-1/-1 -1/-1/-1 -1/-1/-1 
-1/-1/-1 -1/-1/-1 -1/-1/-1 -1/-1/-1 -1/-1/-1 1/-1/-1 -1/-1/-1 1/-1/-1 -1/-1/-1 -1/-1/-1 -1/-1/-1 -1/-1/-1 -1/-1/-1 -1/-1/-1 -1/-1/-1 -1/-1/-1 -1/-1/-1 -1/-1/-1 -1/-1/-1 -1/-1/-1 
-1/-1/-1 -1/-1/-1 -1/-1/-1 -1/-1/-1 -1/-1/-1 1/-1/-1 -1/-1/-1 1/-1/-1 -1/-1/-1 -1/-1/-1 -1/-1/-1 -1/-1/-1 -1/-1/-1 -1/-1/-1 -1/-1/-1 -1/-1/-1 -1/-1/-1 -1/-1/-1 -1/-1/-1 -1/-1/-1 
-1/-1/-1 -1/-1/-1 -1/-1/-1 -1/-1/-1 -1/-1/-1 1/-1/-1 -1/-1/-1 1/-1/-1 -1/-1/-1 -1/-1/-1 -1/-1/-1 -1/-1/-1 -1/-1/-1 -1/-1/-1 -1/-1/-1 -1/-1/-1 -1/-1/-1 -1/-1/-1 -1/-1/-1 -1/-1/-1 
-1/-1/-1 -1/-1/-1 -1/-1/-1 -1/-1/-1 -1/-1/-1 1/-1/-1 13/-1/-1 1/-1/-1 -1/-1/-1 -1/-1/-1 -1/-1/-1 -1/-1/-1 -1/-1/-1 -1/-1/-1 -1/-1/-1 -1/-1/-1 -1/-1/-1 -1/-1/-1 -1/-1/-1 -1/-1/-1 
-1/-1/-1 -1/-1/-1 -1/-1/-1 -1/-1/-1 -1/-1/-1 1/-1/-1 1/-1/-1 1/-1/-1 -1/-1/-1 -1/-1/-1 -1/-1/-1 -1/-1/-1 -1/-1/-1 -1/-1/-1 -1/-1/-1 -1/-1/-1 -1/-1/-1 -1/-1/-1 -1/-1/-1 -1/-1/-1 
</content>
    <position>3 5</position>
    <gravity>1</gravity>
    <tutorial />
    <official />
    <messages>
      <message value="0">Red blocks can be inverted.</message>
      <message value="1">The dark green square invert the red blocks.
The ones that blocked you now let you pass through, and vice-versa.</message>
      <message value="2">Passing through a red portal teleports you to the nearest red portal.
Keep in mind that your inertia is inchanged!</message>
      <message value="3">The blue portals are quite similar, but invert your inertia.</message>
      <message value="4">That's the end of the level. Be prepared to die in the next level, just saying...</message>
    </messages>
    <next-map>4 - Death is upon yous</next-map>
  </map>
  <map>
    <name>2 - Jump and gravity pads</name>
    <width>20</width>
    <height>15</height>
    <content>
1/-1/-1 1/-1/-1 1/-1/-1 1/-1/-1 1/-1/-1 1/-1/-1 1/-1/-1 1/-1/-1 1/-1/-1 1/-1/-1 1/-1/-1 1/-1/-1 1/-1/-1 1/-1/-1 1/-1/-1 1/-1/-1 1/-1/-1 1/-1/-1 1/-1/-1 1/-1/-1 
1/-1/-1 -1/-1/-1 -1/-1/-1 -1/-1/-1 -1/-1/-1 -1/-1/-1 -1/-1/-1 -1/-1/-1 -1/-1/-1 -1/-1/-1 -1/-1/-1 -1/-1/-1 1/-1/-1 -1/3/m4 2/3/m4 -1/3/m4 -1/-1/-1 6/-1/-1 -1/-1/-1 1/-1/-1 
1/-1/-1 -1/-1/-1 -1/-1/-1 2/-1/-1 -1/-1/-1 -1/-1/-1 -1/-1/-1 -1/-1/-1 2/-1/-1 -1/-1/-1 -1/-1/-1 -1/-1/-1 1/-1/-1 -1/3/m4 -1/3/m4 -1/3/m4 -1/-1/-1 -1/-1/-1 -1/-1/-1 1/-1/-1 
1/-1/-1 -1/-1/-1 -1/-1/-1 -1/-1/-1 -1/-1/-1 -1/-1/-1 -1/-1/-1 -1/-1/-1 -1/-1/-1 -1/-1/-1 -1/-1/-1 -1/-1/-1 1/-1/-1 -1/3/m4 -1/3/m4 -1/3/m4 -1/-1/-1 -1/-1/-1 -1/-1/-1 1/-1/-1 
1/-1/-1 -1/-1/-1 -1/-1/-1 -1/-1/-1 -1/-1/-1 -1/-1/-1 -1/-1/m1 -1/-1/m1 -1/-1/m1 -1/-1/m1 -1/-1/m1 -1/-1/-1 1/-1/-1 -1/3/m4 -1/3/m4 -1/3/m4 -1/-1/-1 -1/-1/-1 -1/-1/-1 1/-1/-1 
1/-1/-1 -1/-1/-1 -1/-1/-1 -1/-1/-1 -1/-1/-1 -1/-1/-1 -1/-1/m1 -1/-1/m1 -1/-1/m1 -1/-1/m1 -1/-1/m1 -1/-1/-1 1/-1/-1 -1/3/m4 -1/3/m4 -1/3/m4 -1/-1/-1 -1/-1/-1 -1/-1/-1 1/-1/-1 
1/-1/-1 -1/-1/-1 -1/-1/-1 2/-1/-1 -1/-1/-1 -1/-1/-1 -1/-1/m1 -1/-1/m1 -1/-1/m1 -1/-1/m1 -1/-1/m1 -1/-1/-1 1/-1/-1 -1/3/m4 -1/3/m4 -1/3/m4 1/-1/-1 1/-1/-1 1/-1/-1 1/-1/-1 
1/-1/-1 -1/-1/-1 -1/-1/-1 -1/-1/-1 -1/-1/-1 -1/-1/-1 -1/-1/m1 -1/-1/m1 -1/-1/m1 -1/-1/m1 -1/-1/m1 -1/-1/-1 1/-1/-1 -1/3/m4 -1/3/m4 -1/3/m4 1/-1/-1 -1/-1/-1 -1/-1/-1 -1/-1/-1 
1/-1/-1 -1/-1/-1 -1/-1/-1 -1/-1/-1 -1/-1/-1 -1/-1/-1 1/-1/-1 1/-1/-1 1/-1/-1 1/-1/-1 1/-1/-1 -1/-1/-1 1/-1/-1 -1/3/m4 -1/3/m4 -1/3/m4 1/-1/-1 1/-1/-1 1/-1/-1 1/-1/-1 
1/-1/-1 -1/-1/-1 -1/-1/-1 -1/-1/-1 -1/-1/-1 -1/-1/-1 1/-1/-1 -1/-1/-1 -1/-1/-1 -1/-1/-1 1/-1/-1 -1/-1/-1 1/-1/-1 -1/-1/-1 -1/-1/-1 -1/-1/-1 1/-1/-1 -1/-1/m3 -1/-1/m3 1/-1/-1 
1/-1/-1 -1/-1/m0 -1/-1/m0 2/-1/m0 -1/-1/m0 -1/-1/m0 1/-1/-1 -1/-1/-1 -1/-1/-1 -1/-1/-1 1/-1/-1 -1/-1/-1 1/-1/-1 -1/-1/m2 -1/-1/m2 -1/-1/m2 1/-1/-1 -1/-1/m3 -1/-1/m3 1/-1/-1 
1/-1/-1 -1/-1/m0 -1/-1/m0 -1/-1/m0 -1/-1/m0 -1/-1/m0 1/-1/-1 -1/-1/-1 -1/-1/-1 -1/-1/-1 1/-1/-1 -1/-1/-1 1/-1/-1 -1/-1/m2 -1/-1/m2 -1/-1/m2 1/-1/-1 -1/-1/m3 -1/-1/m3 1/-1/-1 
1/-1/-1 -1/-1/m0 -1/-1/m0 -1/-1/m0 -1/-1/m0 4/-1/m0 1/-1/-1 -1/-1/-1 -1/-1/-1 -1/-1/-1 1/-1/-1 -1/-1/-1 -1/-1/-1 -1/-1/m2 -1/-1/m2 -1/-1/m2 -1/-1/-1 -1/-1/-1 -1/-1/-1 1/-1/-1 
1/-1/-1 -1/-1/m0 -1/-1/m0 -1/-1/m0 -1/-1/m0 -1/-1/m0 1/-1/-1 -1/-1/-1 -1/-1/-1 -1/-1/-1 1/-1/-1 -1/-1/-1 -1/-1/-1 -1/-1/m2 -1/-1/m2 -1/-1/m2 -1/-1/-1 -1/-1/-1 5/-1/-1 1/-1/-1 
1/-1/-1 1/-1/-1 1/-1/-1 1/-1/-1 1/-1/-1 1/-1/-1 1/-1/-1 -1/-1/-1 -1/-1/-1 -1/-1/-1 1/-1/-1 1/-1/-1 1/-1/-1 1/-1/-1 1/-1/-1 1/-1/-1 1/-1/-1 1/-1/-1 1/-1/-1 1/-1/-1 
</content>
    <position>3 13</position>
    <gravity>1</gravity>
    <tutorial />
    <official />
    <messages>
      <message value="0">This one seems a little bit high...
Try to jump on the brown circle on your right.</message>
      <message value="1">Pretty cool right?
Jump Pads allow you to reach higher spots.</message>
      <message value="2">Even with a Jump Pad, the next level seems quite far.
Maybe with these blue circles...</message>
      <message value="3">Gravity Pads invert the gravity.
You can reach the next level now!</message>
      <message value="4">What you just step into is water.
It prevents you from seeing torches, but allows you to freely swim.</message>
    </messages>
    <next-map>3 - Special blocks</next-map>
  </map>
  <map>
    <name>4 - Death is upon you</name>
    <width>35</width>
    <height>14</height>
    <content>
-1/-1/-1 -1/-1/-1 -1/-1/-1 -1/-1/-1 -1/-1/-1 -1/-1/-1 -1/-1/-1 -1/-1/-1 1/-1/-1 1/-1/-1 1/-1/-1 1/-1/-1 1/-1/-1 1/-1/-1 1/-1/-1 1/-1/-1 1/-1/-1 -1/-1/-1 -1/-1/-1 -1/-1/-1 -1/-1/-1 1/-1/-1 1/-1/-1 1/-1/-1 -1/-1/-1 -1/-1/-1 -1/-1/-1 -1/-1/-1 -1/-1/-1 -1/-1/-1 -1/-1/-1 -1/-1/-1 -1/-1/-1 -1/-1/-1 -1/-1/-1 
-1/-1/-1 -1/-1/-1 -1/-1/-1 -1/-1/-1 -1/-1/-1 -1/-1/-1 -1/-1/-1 1/-1/-1 1/-1/-1 -1/-1/-1 -1/-1/-1 -1/-1/-1 -1/-1/-1 -1/-1/-1 -1/-1/-1 -1/-1/-1 1/-1/-1 1/-1/-1 1/-1/-1 1/-1/-1 1/-1/-1 1/-1/-1 13/-1/m1 1/-1/-1 1/-1/-1 1/-1/-1 1/-1/-1 1/-1/-1 -1/-1/-1 -1/-1/-1 -1/-1/-1 -1/-1/-1 -1/-1/-1 -1/-1/-1 -1/-1/-1 
1/-1/-1 1/-1/-1 1/-1/-1 1/-1/-1 1/-1/-1 1/-1/-1 1/-1/-1 1/-1/-1 -1/-1/m0 -1/-1/-1 -1/-1/-1 -1/-1/-1 -1/-1/-1 -1/-1/-1 -1/-1/-1 -1/-1/-1 -1/-1/-1 -1/-1/-1 -1/-1/-1 -1/-1/-1 -1/-1/m1 -1/-1/m1 -1/-1/m1 1/-1/-1 1/-1/-1 12/-1/m-1 16/-1/m1 1/-1/-1 1/-1/-1 1/-1/-1 1/-1/-1 1/-1/-1 1/-1/-1 1/-1/-1 1/-1/-1 
1/-1/-1 -1/-1/m0 -1/-1/m0 -1/-1/m0 -1/-1/m0 -1/-1/m0 2/-1/m0 -1/-1/m0 -1/-1/m0 -1/-1/-1 -1/-1/-1 -1/-1/-1 2/-1/-1 -1/-1/-1 -1/-1/-1 -1/-1/-1 -1/-1/-1 -1/-1/-1 2/-1/-1 -1/-1/-1 -1/-1/m1 -1/-1/m1 -1/-1/m1 -1/-1/m1 2/-1/m1 12/-1/m1 12/-1/m1 12/-1/m1 2/-1/-1 -1/-1/-1 -1/-1/-1 -1/-1/-1 -1/-1/-1 -1/-1/-1 1/-1/-1 
1/-1/-1 -1/-1/m0 -1/-1/m0 -1/-1/m0 -1/-1/m0 -1/-1/m0 -1/-1/m0 -1/-1/m0 -1/-1/m0 -1/-1/-1 -1/-1/-1 -1/-1/-1 -1/-1/-1 -1/-1/-1 -1/-1/-1 -1/-1/-1 -1/-1/-1 -1/-1/-1 -1/-1/-1 -1/-1/-1 -1/-1/m1 -1/-1/m1 -1/-1/m1 -1/-1/m1 -1/-1/m1 -1/-1/m1 -1/-1/m1 -1/-1/m1 -1/-1/-1 -1/-1/-1 -1/-1/-1 -1/-1/-1 6/-1/-1 -1/-1/-1 1/-1/-1 
1/-1/-1 -1/-1/m0 -1/-1/m0 -1/-1/m0 -1/-1/m0 -1/-1/m0 -1/-1/m0 -1/-1/m0 -1/-1/m0 -1/-1/-1 -1/-1/-1 -1/-1/-1 -1/-1/-1 -1/-1/-1 -1/-1/-1 -1/-1/-1 -1/-1/-1 -1/-1/-1 -1/-1/-1 -1/-1/-1 -1/-1/m1 -1/-1/m1 -1/-1/m1 -1/-1/m1 -1/-1/m1 -1/-1/m1 -1/-1/m1 -1/-1/m1 -1/-1/-1 -1/-1/-1 -1/-1/-1 -1/-1/-1 -1/-1/-1 -1/-1/-1 1/-1/-1 
1/-1/-1 1/-1/-1 1/-1/-1 1/-1/-1 1/-1/-1 1/-1/-1 1/-1/-1 1/-1/-1 -1/-1/m0 -1/-1/-1 -1/-1/-1 -1/-1/-1 1/-1/-1 -1/-1/-1 -1/-1/-1 -1/-1/-1 -1/-1/-1 1/-1/-1 -1/-1/-1 -1/-1/-1 1/-1/-1 1/-1/-1 1/-1/-1 1/-1/-1 1/-1/-1 1/-1/-1 1/-1/-1 1/-1/-1 1/-1/-1 1/-1/-1 1/-1/-1 1/-1/-1 1/-1/-1 1/-1/-1 1/-1/-1 
-1/-1/-1 1/-1/-1 2/-1/-1 -1/-1/-1 -1/-1/-1 -1/-1/-1 -1/-1/-1 1/-1/-1 1/-1/-1 -1/7/-1 -1/7/-1 -1/7/-1 -1/7/-1 -1/7/-1 -1/7/-1 -1/7/-1 1/-1/-1 1/-1/-1 -1/-1/-1 -1/-1/-1 1/-1/-1 -1/-1/-1 -1/-1/-1 -1/-1/-1 -1/-1/-1 -1/-1/-1 -1/-1/-1 -1/-1/-1 -1/-1/-1 -1/-1/-1 -1/-1/-1 -1/-1/-1 -1/-1/-1 -1/-1/-1 -1/-1/-1 
-1/-1/-1 1/-1/-1 13/-1/-1 -1/-1/-1 10/-1/-1 -1/-1/-1 -1/-1/-1 -1/-1/-1 1/-1/-1 -1/7/-1 -1/7/-1 -1/7/-1 -1/7/-1 -1/7/-1 -1/7/-1 -1/7/-1 1/-1/-1 -1/-1/-1 -1/-1/-1 -1/-1/-1 1/-1/-1 -1/-1/-1 -1/-1/-1 -1/-1/-1 -1/-1/-1 -1/-1/-1 -1/-1/-1 -1/-1/-1 -1/-1/-1 -1/-1/-1 -1/-1/-1 -1/-1/-1 -1/-1/-1 -1/-1/-1 -1/-1/-1 
-1/-1/-1 1/-1/-1 -1/-1/-1 -1/-1/-1 -1/-1/-1 -1/-1/-1 -1/-1/-1 -1/-1/-1 1/-1/-1 2/7/-1 -1/7/-1 -1/7/-1 -1/7/-1 -1/7/-1 -1/7/-1 2/7/-1 1/-1/-1 -1/-1/-1 -1/-1/-1 -1/-1/-1 1/-1/-1 -1/-1/-1 -1/-1/-1 -1/-1/-1 -1/-1/-1 -1/-1/-1 -1/-1/-1 -1/-1/-1 -1/-1/-1 -1/-1/-1 -1/-1/-1 -1/-1/-1 -1/-1/-1 -1/-1/-1 -1/-1/-1 
-1/-1/-1 1/-1/-1 1/-1/-1 1/-1/-1 1/-1/-1 1/-1/-1 -1/-1/-1 -1/-1/-1 1/-1/-1 1/-1/-1 1/-1/-1 1/-1/-1 1/-1/-1 1/-1/-1 1/-1/-1 1/-1/-1 1/-1/-1 -1/-1/-1 -1/-1/-1 1/-1/-1 1/-1/-1 -1/-1/-1 -1/-1/-1 -1/-1/-1 -1/-1/-1 -1/-1/-1 -1/-1/-1 -1/-1/-1 -1/-1/-1 -1/-1/-1 -1/-1/-1 -1/-1/-1 -1/-1/-1 -1/-1/-1 -1/-1/-1 
-1/-1/-1 -1/-1/-1 -1/-1/-1 -1/-1/-1 -1/-1/-1 1/-1/-1 -1/-1/-1 2/-1/-1 -1/-1/-1 -1/-1/-1 -1/-1/-1 -1/-1/-1 -1/-1/-1 -1/-1/-1 -1/-1/-1 -1/-1/-1 -1/-1/-1 2/-1/-1 -1/-1/-1 1/-1/-1 -1/-1/-1 -1/-1/-1 -1/-1/-1 -1/-1/-1 -1/-1/-1 -1/-1/-1 -1/-1/-1 -1/-1/-1 -1/-1/-1 -1/-1/-1 -1/-1/-1 -1/-1/-1 -1/-1/-1 -1/-1/-1 -1/-1/-1 
-1/-1/-1 -1/-1/-1 -1/-1/-1 -1/-1/-1 -1/-1/-1 1/-1/-1 -1/-1/-1 -1/-1/-1 -1/-1/-1 -1/-1/-1 -1/-1/-1 -1/-1/-1 -1/-1/-1 -1/-1/-1 -1/-1/-1 -1/-1/-1 -1/-1/-1 -1/-1/-1 -1/-1/-1 1/-1/-1 -1/-1/-1 -1/-1/-1 -1/-1/-1 -1/-1/-1 -1/-1/-1 -1/-1/-1 -1/-1/-1 -1/-1/-1 -1/-1/-1 -1/-1/-1 -1/-1/-1 -1/-1/-1 -1/-1/-1 -1/-1/-1 -1/-1/-1 
-1/-1/-1 -1/-1/-1 -1/-1/-1 -1/-1/-1 -1/-1/-1 1/-1/-1 1/-1/-1 1/-1/-1 1/-1/-1 1/-1/-1 1/-1/-1 1/-1/-1 1/-1/-1 1/-1/-1 1/-1/-1 1/-1/-1 1/-1/-1 1/-1/-1 1/-1/-1 1/-1/-1 -1/-1/-1 -1/-1/-1 -1/-1/-1 -1/-1/-1 -1/-1/-1 -1/-1/-1 -1/-1/-1 -1/-1/-1 -1/-1/-1 -1/-1/-1 -1/-1/-1 -1/-1/-1 -1/-1/-1 -1/-1/-1 -1/-1/-1 
</content>
    <position>3 5</position>
    <gravity>1</gravity>
    <tutorial />
    <official />
    <messages>
      <message value="0">Let's make it simple.. Acid kills you.</message>
      <message value="1">A bit more vicious, lasers can kill you too.
Their beam will be stop by any obstacle though...</message>
    </messages>
    <next-map>1 - Basics</next-map>
  </map>
</maps>